{
  "FAN_MODEL_NORMAL": "Normálny",
  "FAN_MODEL_NATURAL": "Prirodzený",
  "FAN_MODEL_SLEEP": "Spánok",
  "CHECK_OPEN_FAN": "Prosím, zapnite ventilátor",
  "CHECK_SENSOR_LINK": "Nepodarilo sa načítať dáta zo snímača, overte si jeho správne pripojením",
  "SHAKE": "Oscilovať",
  "MODEL": "Režim",
  "GEAR": "Rychlosť",
  "PERFORMLOG_SUCCESS": "Úspech",
  "PERFORMLOG_FAIL": "Zlyhanie",
  "MODIFY_CHANNEL_NAME_ERROR": "Nepodarilo sa zmeniť názov kanála. Meno kanála nesmie byť prázdne.",
  "WEIXIN_PUBLISH": "WeChat",
  "CURRENT_NETWORK_NOT_USABLE": "Nie je k dispozícii žiadna SIEŤ, overte si pripojenie k sieti alebo to skúste znova.",
  "SWITCH_ON": "ON",
  "SWITCH_OFF": "OFF",
  "EDIT_SCEN_SUCCESS": "Úprava bola úspešná !!",
  "CHECK_PASSWORD": "Potvrdiť heslo",
  "HAS_ACCOUNT_LOGIN": "Máte účet? Prihláste sa tu",
  "removeSenc": "Del",
  "EDIT_SCEN": "Upraviť scénu",
  "KEEP": "Zachovať stav",
  "SCEN_NAME": "Názov scény",
  "Add_Scenario": "Pridať scénu",
  "EDIT_GROUP": "Upraviť skupinu",
  "DELETE_GROUP": "Odstrániť skupinu",
  "EDIT_GROUP_SUCCESS": "Skupina bola úspešne zmenené!",
  "CREATE_GROUP_SUCCESS": "Skupina bola úspešne vytvorená!",
  "DELETE_GROUP_SUCCESS": "Skupina bola úspešne odstránená!",
  "SURE_DELETE_GROUP": "Naozaj chcete túto skupinu odstrániť?",
  "SELECTED": "Vybraná",
  "ADD_GROUP_NAMING": "Názov skupiny",
  "DEVICE_ERROR_ADD": "Zariadenie bolo úspešne pridané!",
  "MANUAL_MODEL": "Manual",
  "AUTO_MODEL": "Auto",
  "ILLEGAL_ACCOUNT": "Neplatný účet",
  "NO_REGISTER": "Účet neexistuje, prosím, zaregistrujte sa.",
  "EMAIL_ILEGAL": "Neplatná emailová adresa, skúste ju zadať znovu.",
  "EMAIL": "Email",
  "Temporary_does_not_support": "Táto funkcia je dočasne nedostupná.",
  "BACK": "Späť",
  "temperature_greater": "Viacej ako",
  "temperature_leter": "Menej ako",
  "Humidity_Setting": "Vlhkosť",
  "Humidity_between": "Hodnota vlhkosti musí byť medzi 0-100",
  "Enter_condition": "Zadajte hodnotu",
  "Humidity": "Vlhkosť",
  "ON_HUMITURE": "ZAP",
  "OFF_HUMITURE": "VYP",
  "USER_FEEDBACK": "Spätná väzba",
  "Vibration": "Vibrácie",
  "LOADING": "Načítavam ...",
  "DEVICE_ERROR": "Chyba zariadenia, reštartujte ho vypnutím a potom ho znova pridajte",
  "ADD_DEVICE_FAIL": "Pripojenie zariadenia zlyhalo, overte pripojenie k sieti alebo to skúste znova",
  "DEVICE_ERROR_EMBEZZLE": "Pridanie zariadenia zlyhalo, toto zariadenie už pridal iný používateľ",
  "NEXT": "Ďalej",
  "SUBMIT": "Odoslať",
  "CANCEL": "Zrušiť",
  "OK": "OK",
  "SPEED": "Rýchlosť",
  "DEVICE": "Zariadenie",
  "DEVICE_OFFLINE_UNABLE_UPGRADE": "Zariadenie je odpojené, nemožno vykonať aktualizáciu",
  "DEVICE_GRADED_FAIL_RETRY": "Aktualizácia zlyhala, skúste to znova",
  "SELCT_ONE_DAY": "Vyberte aspoň jeden deň",
  "SELECT_REGION": "Vyberte rozsah",
  "SEND": "Odoslané",
  "ADD_NEW_TIMER": "Nový časovač",
  "Current_equipment_has_no_info": "Žiadne podrobné informácie o aktuálnom zariadení",
  "Current_latest_version": "Najnovšia verzia",
  "Firmware_version": "Verzia firmvéru",
  "PASSWORD_RESET_SUCCESS": "Heslo bolo úspešne obnovené",
  "PASSWORD_CHANGE_SUCCESS": "Heslo bolo úspešne zmenené",
  "USER": "Používateľ:",
  "EVERY_DAY": "Každý deň",
  "HOUR": "Hodina",
  "MINUTE": "Minúta",
  "MIN": "Min",
  "SUN": "Ne",
  "MON": "Po",
  "TUE": "Ut",
  "WED": "St",
  "THU": "Št",
  "FRI": "Pi",
  "SAT": "So",
  "NO_SHARE": "Zariadenie sa zdieľané. Zdieľajte ho!",
  "SHARE_SUCCESS": "Zdieľanie bolo úspešné",
  "LOGIN_FAILED_TRY_AGAIN": "Prihlásenie zlyhalo. Prosím, skúste to neskôr",
  "LOGIN_FAIL_AGAIN": "Platnosť prihlásenia vypršala, prihláste sa znova",
  "REQUEST_ERROR_CHECK": "Nesprávny formát, skontrolujte požadované polia",
  "UNKNOWN_ERROR_TRY_AGAIN": "Neznáma chyba, skúste to znova neskôr",
  "WRONG_ORIGINAL_PASSWORD": "Nesprávne heslo, skúste ešte raz",
  "FAILED_TO_CHANGE_PASSWORD_CHECK_NETWORK": "Nepodarilo sa zmeniť heslo, overte sieťové pripojenie",
  "SINGLE_CHANNEL_SOCKET": "Jednokanálová zásuvka",
  "SINGLE_CHANNEL_SWITCH": "Jednokanálový prepínač",
  "COUNTRY_CODE": "Kód krajiny",
  "FAN": "Ventilátor",
  "SOCKET": "Zásuvka",
  "RESET": "RESET",
  "ENERGIZING": "zapnutie",
  "DEVICE_LIST": "Zoznam zariadení",
  "DEVICE_OFFLINE": "Odpojený",
  "REQUEST_FAILED_CHECK_NETWORK_STATUS": "Operácia zlyhala, overte sieťové pripojenie",
  "UPGRADING_NO_RELEVANT": "Zariadenie sa aktualizuje. Ovládanie nie je povolené",
  "OFFLINE_NO_RELEVANT": "Zariadenie je v odpojenom stave. Ovládanie nie je povolené, overte sieťové pripojenie",
  "PERFORM": "Vykonať",
  "CLOSE": "Zatvoriť",
  "DAY": "Deň",
  "GROUP": "Skupina",
  "DEVICE_SETTING": "Nastavenie zariadenia",
  "REGISTER_SUCCESS": "Registrácia bola úspešná, prihláste sa!",
  "OPERATE": "Obsluhovať",
  "AUTO_SWITCH_WIFI": "Postupujte podľa pokynov, pripojte sa k WiFi",
  "STATE": "Stav",
  "WEEK": "Deň",
  "REQUEST_TIME_OUT": "Požiadavka vypršala!",
  "REMOVE_DEVICE": "Pozor, po odstránení zariadenia ho nemožno ovládať pomocou aplikácie. Naozaj ho chcete odstrániť?",
  "OPERATION_FAIL_CHECK_NETWORK_RETRY": "Operácia zlyhala, overte pripojenie k sieti a skúste to znova neskôr",
  "SUCCED": "úspech",
  "NUMBER_DOES_NOT_EXIST": " Číslo neexistuje, prosím, vykonajte kontrolu",
  "ADD_DEVICE": "Pridať zariadenie",
  "LOG_OUT": "Odhlásiť sa",
  "NEXT_TO": "Ďalšie",
  "CONNECTION_BEGINS_WITH_ITEAD": "Pripojte sa k sieti WiFi ktorej meno začína na ITEAD ... Heslo 12345678",
  "PASSWORD": "Heslo",
  "ONLINE": "Pripojené",
  "OFFLINE": "Odpojené",
  "DATE": "Dátum",
  "DEVICE_NAME": "Názov",
  "ABOUTE_WELINK": "O eWeLink",
  "MANUFACTURE_NAME": "Výrobca:",
  "MANUFACTURE_MODEL": "Model:",
  "ONLY_SHARE": "Iba vlastník môže nastaviť zdieľanie tohto zariadenia",
  "START": "Štart",
  "STOP": "Stop",
  "TITLE": "Nadpis",
  "SHARE_DEVICE": "Zdieľať",
  "DEVICE_INFO": "Informácie o zariadení",
  "TIMER": "Časovač",
  "ADD_NEW": "Pridať nové",
  "MODIFY": "Zmeniť",
  "DELETE": "Vymazať",
  "ENERGIZING_ON": "ZAP",
  "ENERGIZING_OFF": "VYP",
  "HIGHT": "Vysoká",
  "MEDIUM": "Stredná",
  "LOW": "Nízka",
  "REAL_TIME_POWER": "Príkon v reálnom čase",
  "POWER": "Príkon",
  "LOG_OUT_LOGIN": "Odhlásiť sa",
  "MY_DEVICE": "Zariadenie",
  "UPGRADING": "Aktualizujem",
  "TIMER_TYPE": "Typ časovača",
  "CUSTOM": "Užívateľský",
  "SELECT_AREA": "Kód krajiny",
  "PHONE_NUMBER": "Telefónne číslo",
  "Account": "Telefónne číslo alebo e-mailová adresa",
  "EMAIL_ADDRESS": "Emailová adresa",
  "RESET_PASSWORD": "Obnoviť heslo",
  "NO_ACCOUNT_REGISTER": "Registrovať",
  "FORGET_PASSWORD": "Obnoviť heslo",
  "LOGIN": "Login",
  "CHANGE_NICKNAME": "Prezývka",
  "NEW_NICKNAME": "Nová prezývka",
  "SMART_SCENE": "Inteligentná scéna",
  "REGISTER": "Registrovať",
  "NICKNAME": "Prezývka",
  "CURRENT_VERSION": "Aktuálne",
  "SELECT_LANGUAGE": "Jazyk",
  "CHANGE_PASSWORD": "Zmeniť heslo",
  "CHANGE_PASSWORD_TITLE": "Heslo",
  "OLD_PASSWORD": "Staré heslo",
  "NEW_PASSWORD": "Nové heslo",
  "MAR": "Mar",
  "SEP": "Sep",
  "EDIT_DELAY_TIMER_ERROR": "Nemožno upraviť. Skúste to znovu po odstránení alebo deaktivácii existujúcich časovačov.",
  "BRIGHTNESS": "Jas",
  "START_BUT": "Štart",
  "END_BUT": "Stop",
  "REFRESH_POWER": "Obnoviť",
  "ADD_COUNTDOWN": "Pridať časovač odpočítavanie",
  "THISYEAR": "Tento rok",
  "NEXTYEAR": "Budúci rok",
  "FORE_ONE": "Iba raz",
  "TIME": "Čas",
  "FINISH": "OK",
  "TIMER_ACTION": "Zapnúť",
  "REPEAT": "Opakovať",
  "DEVICE_DETAIL_TIMER": "Plánovač",
  "DEVICE_DETAIL_TIMER_DELAY": "Odpočítavanie",
  "DEVICE_DETAIL_SHARE": "Zdieľať",
  "DEVICE_OFFLINE_TEXT": "Zariadenie je odpojené, nemožno ovládať",
  "ELECTRICITY_CONSUMPTION": "kWh",
  "CURRENT_POWER": "Aktuálný príkon",
  "CONNECT_FAMILY_WIFI": "Pripojte sa k domácej Wi-Fi",
  "CONFIRM_GIVE_UP_PAIRED_DEVICE": "Ukončiť párovanie?",
  "RETRY": "Skúste to znova",
  "CANNOT_FIND_DEVICE_CHECK_PROPERTIES": "Nepodarilo sa nájsť zariadenie, skontrolujte konfiguráciu podľa ďalej",
  "DEVICE_MATCHING_FAIL_RESULT": "Párovanie zlyhalo",
  "ADD_DEVICE_RENAME_FAIL": "Pridanie bolo úspešné, ale nepodarilo sa pomenovať zariadenie, použije sa základný názov.",
  "ADD_DEVICE_SUCCESS": "Pridanie bolo úspešné!",
  "NETWORK_AVAILABLE_ADD_DEVICE": "Sieť dostupná, priraďovanie zariadení ...",
  "FINISH_ADD_DEVICE": "Kompletné",
  "NAME_FOR_DEVICE": "Pomenujte toto zariadenie",
  "SAVE_WIFI_PASSWORD": "Zapamätať heslo",
  "WIFI_PASSWORD": "heslo k WiFi",
  "USER_PAGE_GROUP": "Skupina",
  "SCENE_MENU": "Scéna",
  "ENERGIZING_STATE": "Stav napájania",
  "DISABLE_Timer_CANNOT_MOVE_THAN": "Operácia zlyhala! Je podporované iba 20 časovačov (vrátane odpočítavanie a opakovače)",
  "Timer_CANNOT_MOVE_THAN": "Operácia zlyhala! Je podporované iba 8 aktivovaná časovačov (vrátane odpočítavanie a opakovače)",
  "CYCLE_TIMER_LIMIT_2": "Čas nemôže byť 0",
  "CYCLE_TIMER_LIMIT": "Druhý čas by mal byť kratší ako prvý čas",
  "Enabled": "Povolené",
  "START_TIME": "Doba spustenia",
  "CURRENT_GROUP_SELECTED": "Vybrané zariadenie",
  "REMOVE_FOR_OTHER_GROUP": "Presun z ostatných skupín",
  "NO_GROUP_DEVICE": "Zariadenie nemajú skupinu",
  "NEW_DEVICE_GROUP": "Pridať novú skupinu",
  "NO_DEVICE_GROUP": "Žiadne skupiny, stlačte na tlačidlo nižšie a pridajte ho.",
  "DEFAULT": "Dostupné zariadenia",
  "ADD_GROUP": "Pridať novú skupinu",
  "MANAGEMENT_GROUP": "Správa skupiny",
  "SHARE_TO_ME_DEVICE": "Zariadenie zdieľané ostatnými",
  "MY_SHARE_DEVICE": "Zariadenie, ktoré som zdieľal",
  "ALL_DEVICE": "Všetky zariadenia",
  "CYCLE_TIME": "Opakovač",
  "SETTING": "Nastavenia",
  "INVITATION_MESSAGE_SET": "Zasielam ponuku na zdieľanie, čakajte prosím ...",
  "ADD_SCEN_SUCCESS": "Úspešne pridaná!",
  "SCEN_LOG_HISTORY": "História",
  "LogSenc": "Log",
  "FREE_BACK_TEXT": "Zadajte svoju emailovú adresu, aby sme Vám mohli odpovedať.",
  "E_WEILINK_MESSAGE_1": "eWeLink je univerzálná bezplatná APka pre inteligentné domácnosti. Umožní Vám vzdialene ovládať a nastavovať Vaše obľúbené inteligentné zariadenia rôznych značiek v jedinej aplikácii.",
  "E_WEILINK_MESSAGE_2": "Podporuje monitorovanie stavov zariadení, nastavenie rôznych časových udalostí, zdieľanie ovládanie a nastavenie scén pre zapnutie alebo vypnutie.",
  "E_WEILINK_MESSAGE_3": "S eWelinkom, môžete regulovať svietivosť, meniť farbu pre RGB LED. Sledovať teplotu, vlhkosť alebo ďalšie dáta z prostredia prostredníctvom jednotiek SC a TH. V neposlednom rade kontrolovať spotrebu Vašich elektrických spotrebičov a mnoho ďalšieho!",
  "WEIXIN_OPEN": "Kopírovať účet Wech a nasledovať",
  "ENERGIZING_KEEP": "Udržiavať",
  "NETWORK_NOT_UNAVAILABLE": "Sieť nie je k dispozícii",
  "PHONE_NUMBER_HAS_REGISTERED": "Tento účet bol registrovaný.",
  "Air_quality": "Kvalita vzduchu",
  "Air_quality_good": "Dobrá",
  "Air_quality_fine": "Priemerná",
  "Air_quality_wrong": "Nezdravá",
  "TEMPERATURE_COLD": "Chladno",
  "TEMPERATURE_Comfort": "Príjemne",
  "TEMPERATURE_hot": "Teplo",
  "Humidity_NORMAL": "Optimálne ",
  "Humidity_DRY": "Sucho ",
  "Humidity_MOIST": "Vlhko ",
  "NOISE": "Hluk",
  "NOISE_wrangle": "Hlučné",
  "NOISE_quiet": "Ticho",
  "NOISE_normal": "Normálný",
  "WRANGLE": "hlučné",
  "BEAM": "Svetlo",
  "BEAM_LIGHT": "Jasno",
  "BEAM_NORMAL": "Polojasno",
  "BEAM_DUSKY": "Šero",
  "CENTER_Humidity": "Vlhkosť",
  "CENTER_Temperature": "Teplota",
  "HUMIDIFIER_GEARS": "Úroveň vlhkosti",
  "HUMIDIFIER_HYDROPENIA": "doliatie",
  "HUMIDIFIER_NORMAL": "Normálne",
  "DETAIL_STATISTICS": "Štatistika",
  "POWER_SOCKET_RATE": "Sadzba za elektrickú energiu",
  "Electricity": "Poplatok za elektrickú energiu",
  "CURRENT": "Aktuálne",
  "VOLTAGE": "Napätie",
  "DEVICE_ERROR_ID_FORMAT": "ID zariadenie je v nesprávnom formáte",
  "DEVICE_ERROR_NOT_BELONG_BRAND": "Zariadenie nepatrí k tejto značke",
  "DEVICE_ERROR_FIND_BRAND_FAILED": "Nepodarilo sa vyhľadať značku",
  "SCENC_PROMPT": "Výzva na scénu:",
  "SCENC_PROMPT_SUCCESS": "Úspech",
  "SCENC_PROMPT_FAIL": "Zlyhanie",
  "Performs_conditional_none": "Žiadna spúšťací podmienka",
  "no_execution_result": "Neboli pridané žiadne výsledky",
  "scene_click_execute": "Klepnutím spustite",
  "add_scene_conditions": "Pridať podmienku",
  "linkage_equipment_conditions": "Hlavné zariadenie",
  "linkage_equipment_device": "Cieľové zariadenie",
  "ENTER_A_VALUE": "Zadajte hodnotu",
  "PLEASE_SELECT_DEVICE": "Vyberte zariadenie",
  "CURRENT_SCENE_NO_DEVICE": "V tejto scéne nie sú žiadne zariadenia",
  "DEVICE_NAME_CAN_NOT_BE_NULL": "Zadajte názov zariadenia",
  "abnormal_Temperature_Value": "Rozsah teplôt: -999 ~ 999",
  "EVERY": "Reštart cyklus:",
  "TIMER_PERMISSIONS": "Oprávnenie časovača",
  "NO_TIMER_PERMISSIONS": "Zatiaľ nemáte oprávnenie, požiadajte majiteľa zariadenia o povolenie na úpravu časovača",
  "DURATION": "Čas:",
  "ongoing": "Spustený",
  "HASENDED": "Dokončený",
  "START_AGAIN": "Spustiť znova",
  "DEVICE_INFO_NOKE_MORE": "Viac",
  "Operation_records": "Prevádzkové záznamy",
  "Operation_records_detail": "Oznámenie operácií pre ovládanie hardvéru a zdieľanie",
  "THINK_CHANGE": "Naskenujte QR kód",
  "CARD_NUMBER": "Číslo karty",
  "DEVICE_UPGRADEING": "Aktualizácia firmvéru ...",
  "NOT_VALID_CODE": "Neplatný QR kód",
  "OPERATION_ACTION": "Stav",
  "OPERATION_TIME": "Čas",
  "FAIL_TO_SEND_SMS": "Nepodarilo sa odoslať overovací SMS kód, skúste to znova",
  "NO_TIMER_DELAY": "Nie je zadaný žiadny čítač pre odpočet, kliknite na tlačidlo nižšie pre pridanie!",
  "RGB_WHITE_LIGHT": "Biela",
  "RGB_COLOURFUL_LIGHT": "Farba",
  "RGB_SCENARIO": "Scéna",
  "RGB_DUSKY": "Tmavá",
  "RGB_LIGHT": "Jasná",
  "RGB_COLD": "Studená",
  "RGB_WARM": "Teplá",
  "RGB_GoodNight": "Odpočinok",
  "RGB_Reading": "Čítanie",
  "RGB_Party": "Párty",
  "RGB_Leisure": "Náhodný",
  "Fahrenheit": "Fahrenheit",
  "SELECT_NEST_DEVICE": "Vyberte zariadenie Nest",
  "NEST_CURRENT_Temperature": "Aktuálna teplota.",
  "NEST_TARGET_Temperature": "Cieľová teplota.",
  "NEST_CURRENT_Humidity": "Vlhkosť",
  "NEST_HOME": "Niekto doma",
  "NEST_AWAY": "Nikto doma",
  "NEST_DEVICE_CANCEL_AUTHORIZATION": "Nest authorita zrušil",
  "NEST_HOME_OR_AWAY": "Niekto doma?",
  "CLICK_RESEND_SMS": "Ak chcete získať verifikačný kód, kliknite na tlačidlo \"odoslať\"",
  "AROMATHERAPY_NIGHT_LIGHT": "Noc",
  "AROMATHERAPY_SMALL": "nízka",
  "AROMATHERAPY_BIG": "vysoká",
  "AROMATHERAPY_WATER_LEVEL": "Objem vody",
  "AROMATHERAPY_WATER_LEVEL_NORMAL": "normal",
  "AROMATHERAPY_WATER_LEVEL_SHORTAGE": "nedostatok",
  "AROMATHERAPY_LIGHT_SWITCH": "Zapnite svetlo",
  "NEST_ACCOUNT_NOT_HAS_DEVICE": "Nie je možné pridať žiadne NEST zariadenie",
  "Threshold": "Hraničná hodnota",
  "Threshold_SET_SUCCESS": "Prahová hodnota je úspešne nastavená!",
  "LONG_PRESS_TO_STUDY": "Stlačením a podržaním tlačidla prejdete do režimu učenia",
  "RF_BRIDGE_SHARE": "Zdieľať",
  "RF_BRIDGE_ADD": "Pridať RF zariadenie",
  "RF_BRIDGE_TIMER": "Plánovač",
  "RF_BRIDGE_DELAY": "Odpočítavanie",
  "RF_BRIDGE_ADD_SINGLE_BUTTOM": "1-tl.",
  "RF_BRIDGE_ADD_DOUBLE_BUTTOM": "2-tl.",
  "RF_BRIDGE_ADD_THREE_BUTTOM": "3-tl.",
  "RF_BRIDGE_ADD_FOUNT_BUTTOM": "4-tl.",
  "RF_BRIDGE_ADD_CURTAIN": "Záves",
  "RF_BRIDGE_ADD_ALARM": "Alarm",
  "RF_BRIDGE_STOP": "Stop",
  "RF_BRIDGE_MAX_ADD": "Podpora až 4 RF Remotes",
  "RF_BRIDGE_BUTTONNAME": "Názov tlačidla",
  "RF_BRIDGE_REMOTE": "Moje RF zariadenie",
  "RF_BRIDGE_LEARNING_STATE": "RF zariadenie je v režime učenia, stlačte tlačidlo diaľkového ovládača alebo nechajte alarmové zariadenie zhasnúť za 1 minútu",
  "RF_BRIDGE_NOT_STUDY": "Tlačidlo ešte nebolo naučené",
  "RF_BRIDGE_RECENTLY_ALARM": "Posledné alarmy",
  "TIMER_SET_DHM_ZERO": "Chyba času, prosím nenastavujte zastaraný časovač",
  "RF_BRIDGE_HAS_NO_STUDY_REMOTE": "K dispozícii nie sú RF zariadenia",
  "RF_BRIDGE_NO_REMOTELEARNING_RULES": "Žiadne povolenie",
  "RF_BRIDGE_REMOTE_NAME": "Názov RF zariadenia",
  "RF_BRIDGE_REMOTE_BUTTON": "Tlačidlo",
  "RF_BRIDGE_BUTTONNAME_NAME": "Názov",
  "RF_BRIDGE_CHANGE_NAME_TITLE": "Edituj Názov",
  "RF_BRIDGE_LONGPRESS_TIMEOUT": "Časový limit!",
  "ADD_DEVICE_ONLY_SUPPORT_WIFI": "Podporuje iba 2.4G WiFi",
  "SCENE_EXECUTE_POWER_KEEY": "Udržovať",
  "SCENE_EXECUTE_EXECUTE_ALL_SELECT_KEEP": "Nemôžete nastaviť stav všetkých kanálov ako Udržovať",
  "USER_FAQ_QUESTION": "Párovanie zlyhalo ...",
  "USER_FAQ": "FAQ",
  "USER_ECHO": "Amazon Echo",
  "USER_GOOGLE_HOME": "Google Home",
  "User_GOOGLE_NEST": "Google Nest",
  "COLOR_MODEL": "Farebný režim",
  "CUSTOM_COLORS": "Vlastná farba",
  "CUSTOM_COLORS_TEXT": "(Stlačením a podržaním tlačidla DIY uložte vybranú farebnú alebo farebnú teplotu)",
  "Only_The_Owner": "Iba vlastník môže spracovať",
  "LIGHT_BELT_COLOR_MODEL_SELECT": "Vyberte režim",
  "LIGHT_BELT_COLOR_MODEL_SELECT_2": "Mode 2: Gradiant",
  "LIGHT_BELT_COLOR_MODEL_SELECT_3": "Mode 3: Jump",
  "LIGHT_BELT_COLOR_MODEL_SELECT_SHEEP": "Rýchlosť",
  "ONLY_COMMON_MODE_DIY": "Iba normálny režim podporuje DIY",
  "DEVICE_LIST_TRACK_ON": "Open",
  "DEVICE_LIST_TRACK_OFF": "Close",
  "DEVICE_LIST_TRACK_PAUSE": "Stop",
  "DEVICE_DETAIL_TRACK_ON": "Open",
  "DEVICE_DETAIL_TRACK_OFF": "Close",
  "VIBRATE_SWITCH": "Prepínač vibrácií",
  "not_device": "Zariadenie neexistuje",
  "fine": "Výborný",
  "middle": "Stredný",
  "bad": "Zlý",
  "air": "Vzduch:",
  "temperature": "Teplota:",
  "c": "Celzia",
  "humidity": "Vlhkosť:",
  "not_internet_current": "Žiadna dostupná sieť",
  "online": "(Pripojené)",
  "offline": "(Odpojené)",
  "device_offline": "Zariadenie je odpojené, nemôžete ho teraz ovládať",
  "info_sure_delete": "Naozaj chcete odstrániť toto zariadenie?",
  "ok": "OK",
  "Save": "Ulož",
  "cancel": "Zrušiť",
  "delete_group": "Všetky zariadenia odstránenej skupiny budú stále existovať. Určite chcete zmazať skupinu?",
  "waiting": "Čakajte prosim ...",
  "device_name_not": "Názov zariadenia nesmie byť prázdny",
  "timer": "Časovač",
  "once": "Raz",
  "day": "Denne",
  "days": "Pracovné dni",
  "week": "Týždeň",
  "date": "deň",
  "commit": "Odoslať",
  "password_not": "Heslo nemôže byť prázdne",
  "resend": "znovu odoslať",
  "name_not": "Prezývka nemôže byť prázdna",
  "modify_name_success": "úspešne aktualizované",
  "modify_name_failed": "Úprava prezývku zlyhala",
  "sms_code": "Odoslať kód",
  "old_paswd_not": "Staré heslo nemôže byť prázdne",
  "new_paswd_not": "Nové heslo nemôže byť prázdne",
  "secondary_not": "Potvrdenie hesla nemôže byť prázdne",
  "two_passwords_notsam": "Heslá sa nezhodujú",
  "info_old_paswd": "Heslo musí obsahovať aspoň 8 znakov",
  "info_fomat_paswd": "Minimálne 8 znakov",
  "info_fomat_email": "Zadajte platnú emailovú adresu",
  "change_susess": "Zmeny boli úspešné",
  "user": "Používateľ",
  "user_online": "Užívateľ odpojený",
  "user_exist": "Užívateľ neexistuje",
  "user_denied": "Odmietnuté",
  "enter_phone_number": "Nesprávne telefónne číslo",
  "not_share_own": "Zdieľanie sám sebe nie je povolené",
  "has_share": "už zdieľané",
  "enter_not_null": "Vstup nemôže byť prázdný",
  "login_failed": "Prihlásenie neprebehlo, zlý účet alebo heslo",
  "register_failed": "Registrácia zlyhala",
  "not_internet": "Žiadna dostupná sieť",
  "add_group": "Nová skupina",
  "my_device": "Moje zariadenie",
  "repeat": "Opakovať",
  "one": "Jedna",
  "two": "Dva",
  "three": "Tri",
  "four": "Štyri",
  "switch_on": "ZAP",
  "off_switch": "VYP",
  "modify_nickname": "Upraviť prezývku",
  "share": "Zdieľať",
  "register": "Registrovať",
  "feedback": "Spätná väzba",
  "login": "Prihlásiť sa",
  "next": "Ďalšie",
  "loading": "načítavanie ...",
  "enter_group_name": "Názov vstupnej skupiny",
  "upgrade": "Aktualizácia",
  "enter_device_name": "Zadajte nový názov",
  "my_devices": "Moje zariadenia",
  "delete": "Odstrániť",
  "minutes": "minút neskôr",
  "cut": "Vystrihnúť",
  "reciver_invite": "Užívateľ %1$s chce zdieľať s vami %2$s. Súhlasíte?",
  "select_wifi": "Vyberte WiFi sieť",
  "input_phone": "Zadajte telefónne číslo",
  "input_email": "Zadajte emailovú adresu",
  "name_or_pwd_is_empty": "Užívateľské meno alebo heslo je prázdne",
  "account_notvalid": "Neplatný účet",
  "input_account": "Prosím, zadajte svoj účet",
  "phone_notvalid": "Neplatné telefónne číslo",
  "deviceupdate": "Aktualizácia firmvéru, neovládajte opakovane",
  "timers": "Plánovač",
  "weeks": "týždeň",
  "ones": "Po",
  "feedback_success": "Odoslanie bolo úspešné",
  "usernot_exsit": "Užívateľ neexistuje, zaregistrujte sa",
  "feedback_fail": "Odoslanie zlyhalo",
  "version": "Test",
  "error_sms_code": "Nesprávny overovací kód, skúste to znova",
  "send_email_fail_check": "Nepodarilo sa odoslať email, overte stav siete",
  "send_email_fail": "Nepodarilo sa odoslať email",
  "confirm": "Potvrdiť",
  "connectto_nopwd": "Nezadali ste heslo, Ste si istí, že WiFi sieť žiadne nemá?",
  "pwd_no_chinese": "Heslo nemôže obsahovať čínske znaky",
  "infoupgrade": "Firmware môže byť aktualizovaný, prejdite do nastavení zariadenia a vykonajte aktualizáciu",
  "power_on": "ZAP",
  "power_off": "VYP",
  "Info_updateerr": "Zariadenie je odpojené, nemožno ho teraz aktualizovať",
  "hour": "Hodina",
  "check_wifi": "Overte svoju sieť",
  "send_config_over_time": "Vypršal časový limit pre pridanie zariadenia, skúste to znova",
  "switchcountry": "Vyberte svoju krajinu",
  "password": "Heslo",
  "current_version": "Verzia",
  "nickname": "Zadajte novú prezývku",
  "go_on": "Pokračovať",
  "add_device": "Pridať zariadenie",
  "retry": "Skúste to znova",
  "device_list": "Moje zariadenie",
  "change_language": "Zmeniť jazyk",
  "over": "Koniec",
  "connected_device_wait": "Pripájam sa k zariadeniu, čakajte prosím ...",
  "device_has_been_register": "Pozor, toto zariadenie už máte pridané!",
  "add_success": "Úspešne pridané!",
  "device_setting": "Nastavenia",
  "open": "Otvoriť",
  "close": "Zatvoriť",
  "need_permission_coarse": "Udeľte oprávnenie eWeLinku na sieť alebo umiestnenia, inak nebudete môcť pridať zariadení!",
  "operat_fail_retry": "Operácia zlyhala, skúste to neskôr!",
  "auto_model": "Automaticky",
  "auto_model_unable_control": "Ovládať prepínanie v režime Automatiky nie je možné",
  "no_address": "Nevyplnili ste kontaktné informácie, pokračovať?",
  "add_new_scene": "Pridať scénu",
  "scene_name": "Názov scény",
  "please_enter_scene_name": "Zadajte názov scény",
  "execute": "Spustiť",
  "delete_scene": "Vymazať scénu",
  "channel1": "Kanál 1:",
  "channel2": "Kanál 2:",
  "channel3": "Kanál 3:",
  "channel4": "Kanál 4:",
  "keep": "Udržiavať",
  "delete_scene_success": "Scéna bola úspešne odstránená",
  "channel": "Výstup",
  "channel_name": "Názov kanála",
  "production": "Zavedenie výrobku",
  "latest_version": "Najnovšie:",
  "scene_log_detail": "Podrobnosti",
  "success": "Úspech",
  "failed": "Zlyhanie",
  "history": "Záznam histórie",
  "sure_delete_scene": "Naozaj chcete odstrániť túto scénu?",
  "open_switch_first": "Prosím, zapnite vypínač",
  "start": "Štart",
  "end": "Koniec",
  "current_power": "Aktuálna spotreba:",
  "kwh": "kWh",
  "day_power": "Denná spotreba elektrickej energie",
  "jan": "Jan",
  "feb": "Feb",
  "mar": "Mar",
  "apr": "Apr",
  "may": "Máj",
  "june": "Jún",
  "july": "Júl",
  "aug": "Aug",
  "sept": "Sept",
  "oct": "Okt",
  "nov": "Nov",
  "dec": "Dec",
  "current_month_power": "Celkom",
  "current_power_title": "Aktuálna spotreba",
  "history_power": "Záznam o spotrebe",
  "youqiao_not_null_input_thresold": "Zadajte prosím",
  "found_gen_one": "Nájdená prvá generácia zariadenia \\ n% 1 $ s",
  "found_gen_two": "Nájdená druhá generácia zariadenia",
  "device_registing": "Prevedenie registrácie ...",
  "change_net": "Zmeniť WiFi sieť",
  "delete_group_fails": "Skupina nebola odstránená",
  "confirm_to_state_pair": "Párovanie Vášho zariadenia",
  "choose_wifi": "Vyberte WiFi",
  "pairing": "Párovanie ...",
  "pair_failure": "Párovanie zlyhalo",
  "pair_failure_reason_check_device_pair_state": "Vaše zariadenie nie je v režime párovania, Spustite ho.",
  "pair_failure_reason_check_wifi_pwd": "Potvrďte, že ste zadali správne heslo k WiFi sieti",
  "where_it_meet": "Keď je rovnaká:",
  "device_excute": "Vykonať:",
  "select_condition": "Vyberte podmienku",
  "smart_scene": "Inteligentná scéna",
  "confirm_quit_name": "Ukončiť pomenovanie zariadenia?",
  "wifi_name": "WiFi meno",
  "wifi_pwd": "WiFi heslo",
  "choose_device": "Vyberte zariadenie",
  "cardview_device_off_line": "odpojené",
  "back": "Späť",
  "delay_timers": "Časovač",
  "new_timer_time": "Čas",
  "delay": "Časovač",
  "brightness": "Jas",
  "no_custome_timer": "Nie je nastavený žiadny plán. Pridajte nový kliknutím na tlačidlo Nový plán.",
  "has_not_installed_wechat": "Nemáte nainštalovaný Wech",
  "all_device": "Všetky zariadenia",
  "sure_delete": "odstrániť?",
  "scene": "Scéna",
  "group": "Skupina",
  "fan_on": "ZAP",
  "fan_off": "VYP",
  "air_quality": "Kvalita vzduchu",
  "humidity_water_info": "Voda",
  "humidity_on_off": "ZAP / VYP",
  "water_level_shortage": "Nedostatok",
  "auto": "Automaticky",
  "high": "HD",
  "ota_upgrade_alert_info": "Aktualizácia firmvéru môže spôsobiť zmenu stavu zariadenia, pokračovať?",
  "termostat": "Termostat",
  "temperature_setting": "Nastavenie teploty",
  "more": ">",
  "less": "<",
  "device_info_not_be_empty": "Názov zariadenia, ID a apikey nesmie byť prázdne!",
  "add_device_failed": "Pridanie zariadenia zlyhalo!",
  "find_mode_failed": "vyhľadanie modelu sa nepodarilo!",
  "log": "Log",
  "please_choose_device": "Prosím, vyberte zariadenie.",
  "add_condition": "Pridať podmienku",
  "add_execute_device": "Pridať spúštacie zariadenie",
  "please_operater_under_current_device": "Prosím, vyberte operáciu v aktuálnom zariadení!",
  "click_execute": "Spustiť Kliknutím",
  "select_trigger_condition": "Vyberte spúšťaciu podmienku",
  "add_scene": "Pridať scénu",
  "tem_upper_smaller_lower": "Horná hranica teploty by mala byť väčšia než dolná hranica",
  "tem_upper_not_equal_lower": "Horná hranica teploty by sa nemala rovnať spodnej hranici",
  "hum_upper_not_equal_lower": "Horná hranica vlhkosti by mala byť väčšia než dolná hranica",
  "hum_upper_smaller_lower": "Horná hranica vlhkosti by nemala rovnať spodnej hranici",
  "edit_scene": "Upraviť scénu",
  "repeat_condition": "Opakovaná podmienka!",
  "tem_hum_dht11_tem_range": "Rozsah teplôt: 0-50",
  "tem_hum_2301_tem_range": "Rozsah teplôt: -40-80",
  "tem_hum_b20_tem_range": "Rozsah teplôt: -55-125",
  "tem_hum_dht11_hum_range": "Rozsah vlhkosti: 20-90",
  "tem_hum_2301_hum_range": "Rozsah vlhkosti: 0-100",
  "no_userful_device": "Nie sú dostupné žiadne zariadenia",
  "duration_delay": "Po:",
  "light_bigger_more": "Horná hranica svetla by mala byť väčšia než jej dolná hranica",
  "air_bigger_more": "Horná hranica kvality vzduchu by mala byť väčšia než jej dolná hranica",
  "noise_bigger_more": "Horná hranica hluku by mala byť väčšia než jej dolná hranica",
  "copy_success": "Úspešne skopírované",
  "share_permit_timer": "Oprávnenie časovača:",
  "share_not_share_user": "Príjemca odstránil zariadenie",
  "share_not_in_3_minute": "Zdieľanie tomu istému užívateľovi počas 3 minút nie je povolené.",
  "share_time_out_3_minute": "Časový limit zdieľanie",
  "nest_has_person": "Áno",
  "nest_has_no_person": "Nie",
  "add_nest_failed_409": "Nepodarilo sa pridať, toto zariadenie pretože už bolo pridané",
  "nest_humidy_limit": "Rozsah vlhkosti: 0 ~ 100",
  "login_failed_server_error": "Prihlásenie zlyhalo, chyba servera",
  "device_upgrade_success_version": "Firmvér zariadenia bol úspešne aktualizovaný na verziu %1$s",
  "single_device_choose": "Jednokanálové zariadenie",
  "please_input_phone_number": "Číslo karty",
  "gsm_phone_number": "Číslo karty",
  "gsm_package": "Mobilné dáta:",
  "gsm_total": "Dáta celkom:",
  "gsm_used": "Využitie dát:",
  "gsm_has": "Dostupné údaje:",
  "device": "Zariadenie",
  "switch_trigger_type": "Zdroj spustenie",
  "business_cooperation": "Obchodná spolupráca",
  "pair_gsm_device": "Zariadenie GSM",
  "night_light": "Nočné svetlo",
  "water_level": "Hladina vody",
  "remote_control_name_not_empty": "Názov diaľkového ovládania RF nesmie byť prázdny",
  "rf_channel_name_not_empty": "Názov tlačidla nemôže byť prázdny",
  "alarm_history": "História alarmov",
  "has_already_cancel_share": "Zdieľanie zrušené.",
  "aromatherapy_colorful_light": "Farba svetla",
  "Enter_verifycode": "Zadajte overovací kód",
  "beijing_temp_big_more": "Prvá hodnota musí byť väčšia ako druhá.",
  "beijing_temp_big_range": "Teplotný rozsah: 6 ~ 35",
  "beijing_temp_small_range": "Teplotný rozsah: 5 ~ 34",
  "beijing_temp_small_less": "Druhá hodnota musí byť menšia ako prvá",
  "has_already_send_to_you": "Overovací kód bol odoslaný do Vášho telefónu alebo emailovej schránky. Preveďte kontrolu Vašej schránky / telefónu a opíšte ho",
  "login_failed_retry_later": "Prihlásenie zlyhalo, skúste to neskôr",
  "goto_rfbridge_know_more": "Otvorte detaily RF Bridge a dozviete sa viac o histórii poplachov",
  "nest_account_changed": "Zmena účtu Nest odstráni pridané zariadenia Nest, chcete pokračovať?",
  "add_timer": "Nový časovač",
  "unknow": "Neznámy",
  "enter_faq": "Čítať FAQ",
  "you_can_create_scene": "Môžete vytvoriť scénu pre zapnutie / vypnutie viacero zariadení jediným kliknutím.",
  "you_can_create_smart_scene": "Môžete vytvoriť scénu pre spustenie zapnutie / vypnutie zariadenia pomocou dát zo snímačov alebo zmenou stavu ostatných zariadení.",
  "let_your_device_operate_automatically": "Nechajte Vaše zariadenie pracovať automaticky, pokojne môžete zahodiť aj telefón.",
  "sure_device_closer_wifi": "Prosím, uistite sa, že váš telefón a zariadenia sú v blízkosti dosahu WiFi routera.",
  "detail_alert_device_offline": "Zariadenie odpojené",
  "cant_operate_frequently": "Systém čaká na odozvu. Neopakujte operáciu, tak rýchlo",
  "ez_unbind": "Rozpojiť",
  "ez_not_bind": "Ešte neprepojené",
  "has_bound_ewelink": "Bolo prepojené s eWelink účtom",
  "setting": "Nastavenia",
  "ez_camera": "Fluorite kamera",
  "ez_settings_device_serial": "Sériové číslo",
  "ez_current_version": "Súčasná verzia",
  "ez_latest_version": "Najnovšia verzia",
  "detail_defend_c1_c2_f1": "Pripomenutie detekcie aktivity",
  "detail_safe_mode": "Šifrovanie Videá / obrazu",
  "ez_setting": "Nastavenie zariadenia",
  "countdown": "Správa %d zostáva sekúnd",
  "encrypt_password_open_fail_networkexception": "Operácia zlyhala, prosím, overte pripojenie k sieti",
  "encrypt_password_open_fail": "Operácia zlyhala",
  "input_device_verify_code": "Prosím, vložte overovací kód zariadenia",
  "ptz": "Otočná a naklápacie (PTZ)",
  "talk": "Hovoriť",
  "ez_event_message": "Správa",
  "quality_hd": "HD",
  "quality_flunet": "Plynulá",
  "quality_balanced": "Vyrovnaná",
  "capture": "Zaobstarať snímku obrazovky",
  "record": "Nahrať video",
  "remoteplayback_capture_fail_for_memory": "Vytvorenie snímky obrazovky zlyhalo z dôvodu nedostatku miesta v úložisku",
  "already_saved_to_volume": "Uložené v albume",
  "remoteplayback_record_fail": "Nahrávanie zlyhalo",
  "realplay_set_vediomode_fail": "Chyba pri zmene kvality videa",
  "ez_event_message_detail": "Detail správy",
  "from": "Zdroj",
  "fan_light_small": "Málo",
  "fan_light_middle": "Stred",
  "fan_light_high": "Veľa",
  "fan_light": "Svetlo",
  "fan_light_smart": "Inteligentný",
  "fan_light_text": "Ventilátor",
  "fan_light_switch": "Svetlo",
  "month": "Mesiac",
  "light_belt_undiy": "Tlačidlo nemá definovanú farbu",
  "add_success_wait_second": "Úspešne pridané, Zariadenie sa pripája k WiFi sieti, táto operácia môže trvať aj pár minút. Prosím, čakajte.",
  "scene_operate_success": "Úspešne spustené",
  "please_choice_execute_condition": "Prosím pridajte podmienku",
  "no_userful_alarm_device": "Nie sú k dispozícii žiadne poplašné zariadenia",
  "no_userful_remote_device": "Nie sú k dispozícii žiadne diaľkové ovládače",
  "unknow_remote_has_deleted": "Neznáme vzdialené ovládanie (vymazané)",
  "info_sure_delete_and_in_scene": "Naozaj chcete zmazať toto zariadenie? Súvisiacia scéna bude spustená súčasným vymazaním.",
  "no_userful_key": "Nie sú k dispozícii Žiadne tlačidlá",
  "youqiao_big_power": "Maximálna hodnota príkonu je 3300",
  "youqiao_small_power": "Minimálny príkon je 0.1",
  "youqiao_smaller_power_small_than_bigger": "Minimálny príkon musí byť menší ako maximálny príkon",
  "youqiao_big_electric": "Maximálny prúd je 15",
  "youqiao_small_electric": "Minimálny prúd je 0",
  "youqiao_big_valtage": "Maximálne napätie je 300",
  "youqiao_small_valtage": "Minimálne napätie je 0",
  "YOUQIAO_SECOND_TITLE_ALERT": "Prosím nastavte prahové hodnoty pre automatické vypnutie zariadenia.",
  "YOUQIAO_MIN_VALUE": "Min. Prah",
  "YOUQIAO_MAX_VALUE": "Max. Prah",
  "YOUQIAO_OPS": "OPS",
  "POWER_SOCLET_ALARM_TITLE": "Ochranný systém proti preťaženiu",
  "DEVICE_IS_INITING": "Prístroj je inicializovaný",
  "PUSH_ADS_MESSAGE": "Máte novú správu. Chcete sa na nu pozrieť?",
  "CAMERA_PERMISSION_REQUEST": "Táto funkcia vyžaduje použitie funkcie fotoaparátu. Umožňuje vám používať funkciu fotoaparátu?",
  "DEVICE_SCAN_TXT": "Príručka prístroja",
  "SCENE_DIFFERENT_CONDITION": "Podmienky nemôžu byť v rozpore",
  "SCENE_SUBMIT_MESSAGE_NONNULL": "Vyplňte prosím tieto informácie",
  "TIMER_ON": "ZAP",
  "SHARE_UPDATE_FAIL": "aktualizácia zlyhala",
  "UNDIFINE_DEVICE": "nedefinované zariadenie",
  "PARAMS_IS_NUMBER_ONLY": "Tento parameter je možné zadať iba ako celé číslo!",
  "Meteorological_Station": "Meteorologická stanica",
  "SCENE_MODE_Night": "Noc",
  "SCENE_MODE_Candle": "Sviečka",
  "SCENE_MODE_Waking": "Budenie",
  "SCENE_MODE_Forest": "Les",
  "SCENE_MODE_Fireplace": "Krb",
  "SCENE_MODE_Water": "Voda",
  "SCENE_MODE_Working": "Práca",
  "SCENE_MODE_Party": "Párty",
  "Please_unlock_GTH": "Odomknite prosím!",
  "CUN_YOU_DOOR_Lock": "Zamknúť",
  "ADD_DEVICE_FAST_MODE_TEXT": "Režim rýchleho párovanie",
  "ADD_DEVICE_FAST_MODE_MESSAGE_1": "Zapnite zariadenie, potom stlačte a držte párovací tlačidlo počas 5 sekúnd dokiaľ indikačné LED nezačne blikať v cykle 2x krátko, 1x dlho.",
  "ADD_DEVICE_FAST_MODE_MESSAGE_2": "Pre LED žiarovku, pásik alebo zvlhčovač, prosím 3x vypnite / zapnite zariadenie, v časovom intervale 2 sekundy. Indikačné LED začne rýchlo blikať.",
  "ADD_DEVICE_Compatibility_mode_text": "Režim kompatibilného párovanie",
  "ADD_DEVICE_Compatibility_mode_message_android": "Vypnite zariadenie, potom ho znova zapnite. Stlačte a držte párovací tlačidlo počas 5 sekúnd dokiaľ indikačné LED nezačne blikať rýchlejšie. Uvoľnite prst. Stlačte a držte párovací tlačidlo ďalších 5 sekúnd dokiaľ indikačné LED nezačne blikať nepretržite. Pre LED žiarovku , pásik alebo zvlhčovač, prosím 3x vypnite / zapnite zariadenie a potom ešte raz 3x vypnite / zapnite zariadenie. ",
  "TRY_ADD_DEVICE_Compatibility_mode": "Skúste párovať v kompatibilnom režime",
  "ADD_DEVICE_Compatibility_mode_message_ios": "Vypnite zariadenie, potom ho znova zapnite. Stlačte a držte párovací tlačidlo počas 5 sekúnd dokiaľ indikačné LED nezačne blikať rýchlejšie. Uvoľnite prst. Stlačte a držte párovací tlačidlo ďalších 5 sekúnd dokiaľ indikačné LED nezačne blikať nepretržite. Pre LED žiarovku , pásik alebo zvlhčovač, prosím 3x vypnite / zapnite zariadenie a potom ešte raz 3x vypnite / zapnite zariadenie. prosím postupujte podľa pokynov nižšie. ",
  "SHARE_INPUT_NOTE": "Prosím zadajte poznámku",
  "SHARE_NOTE": "Poznámka",
  "SHARE_UPDARE_NOTE": "Aktualizovať poznámku",
  "OLD_NICKNAME": "Stará prezývka",
  "first_larger_second": "Číslo na prvom riadku nesmie byť nižšie ako na druhom riadku",
  "REFRESH_SUCCESS": "Úspešne obnovené",
  "UPDATE_SUBMIT": "Aktualizovať",
  "INPUT_OLD_PASSWORD": "Staré heslo",
  "INPUT_NEW_PASSWORD": "Nové heslo",
  "CONFIRM_NEW_PASSWORD": "Potvrdiť heslo",
  "NO_DATA_STR": "Žiadne dáta",
  "PLEASE_CHOOSE_TITLE": "Zvoľte",
  "RF_BRIDGE_OPEN": "ZAP",
  "RF_BRIDGE_CLOSE": "VYP",
  "new_no_device_alert": "Nemáte spárované žiadne zariadenia. \" Klikni na tlačidlo \"pridať zariadenie nižšie pre spustenie párovanie.",
  "TIMER_OFF": "vypnúť",
  "ON": "ZAP",
  "OFF": "VYP",
  "DEVICE_OF_NEST": "Prepojiť s nest",
  "HOME_KIT_GATEWAY": "Home bridge",
  "HOME_KIT_GET_TEMPCODE_ERROR": "Autorizácia Homekit zlyhala, prosím, overte pripojenie k sieti a skúste to znova",
  "FEEDBACK_INPUT_EMAIL": "Prosím, zadajte svoj email",
  "TIMER_PERMISSIONS_ADD": "Pridať",
  "TIMER_PERMISSIONS_EDIT": "Upraviť",
  "TIMER_PERMISSIONS_DELETE": "Zmazať",
  "share_permit_timer_enable": "Povoliť / Zakázať",
  "CHANNEL": "Kanál",
  "FAIL_TO_SEND_SMS_LIMIT": "Prekročený limit počtu požiadaviek na overovací kód",
  "Note": "Poznámka",
  "MACHINE_BED_AUTO_MODE": "Automatický režim",
  "MACHINE_BED_COMMON_MODE": "Normálny režim",
  "MACHINE_BED_Vibration_strength": "Intenzita vibrácií",
  "MACHINE_BED_Vibration_strength_weak": "Ľahko",
  "MACHINE_BED_Vibration_strength_middle": "Stredne",
  "MACHINE_BED_Vibration_strength_strong": "Silne",
  "MACHINE_BED_Lifting_Angle": "Nastavenie uhla",
  "MACHINE_BED_Lifting_Angle_Back_up": "Zdvíhanie operadla",
  "MACHINE_BED_Lifting_Angle_Back_down": "Klesanie operadla",
  "MACHINE_BED_Lifting_Angle_Back_leg_up": "Zdvíhanie operadla & opierky nôh",
  "MACHINE_BED_Lifting_Angle_Back_leg_down": "Klesanie operadla & opierky nôh",
  "MACHINE_BED_Lifting_Angle_Leg_up": "Zdvíhanie stehennej opierky",
  "MACHINE_BED_Lifting_Angle_thigh_down": "Klesanie stehennej opierky",
  "MACHINE_BED_Lifting_Angle_stop": "Stop",
  "MACHINE_BED_Massage_place": "Masážne zóna",
  "MACHINE_BED_Massage_place_Shoulder_massage": "Ramená",
  "MACHINE_BED_Massage_place_Neck_massage": "Krk",
  "MACHINE_BED_Massage_place_waist_massage": "pás",
  "MACHINE_BED_Massage_place_leg_massage": "Nohy",
  "MACHINE_BED_Negative_ions": "Záporné ióny",
  "Temperature": "Teplota",
  "BEI_JING_MORE_THAN_CLOSE": "Ak je vyššia ako táto hodnota, vypni ho",
  "BEI_JING_UNSER_THAN_CLOSE": "Ak je táto hodnota nižšia, zapni ju",
  "COLORTEMP": "Teplota farby",
  "ez_account": "Účet Fluorite",
  "sure_delete_ezcamera": "Potvrdením zmažete všetky Fluorite kamery zo súčasného účtu.",
  "sure_unbind_account": "Naozaj chcete rozpojiť účet?",
  "current_account_has_no_ez": "Súčasný účet neobsahuje žiadne Fluorite zariadenie",
  "added_camera_verycode_fail_title_txt": "Overenie, ktoré ste zadali je nesprávne, prosím, zadajte znova",
  "remoteplayback_capture_fail": "Chyba pri robení snímky obrazovky",
  "my_smart_socketone": "Moje zariadenia",
  "pair_failure_reason_check_assistant": "Overte nastavenie oprávnení pre mobilné zabezpečenia a antivírusový softvér, uistite sa, že eWeLink má prístup k WiFi.",
  "no_choice_device": "Žiadne voliteľné zariadenie",
  "APP_NAME": "eWeLink",
  "APP_UPDATE": "apk aktualizácia",
  "CANNOT_CONNECT_DEVICE_CHECK_PROPERTIES": "Chyba pri komunikácii. Vykonajte kontrolu podľa nasledujúcej konfigurácie",
  "goto_system_setting": "Potom sa vráťte do eWeLinku. Systémové nastavenia WiFi",
  "pair_failure_reason_check_net_enable": "Chyba, overte, či mobilná sieť funguje štandardne a skúste to znova neskôr",
  "pair_failure_reason_cannot_connect_manual_setting": "Automatické pripojenie k WiFi sieti zariadení zlyhalo, pripojte ho ručne. Udalosti: nastavenie telefónu -> WiFi, pripojte sa k WiFi \" ITEAD - ****** \"s heslom \" 12345678 \".",
  "EZVIZ_CODE_EMPTY": "Overovací kód nemôže byť prázdny",
  "TOTAL_FEE": "Celkom",
  "TOTAL_POWER": "Celkom",
  "verify_code_error": "Nesprávny kód overovania, skontrolujte, prosím",
  "NO_EZVIZ_ALARM_INFO": "Žiadne údaje monitorovania",
  "EZVIZ_VEDIO_FAILED": "Nahrávanie zlyhania videa",
  "EZVIZ_PLAY_FAILED_BECAUSEOF_NET": "Nepodarilo sa prehrať video, skontrolujte sieťové pripojenie",
  "SWEEPING_ROBOT_MODE_FIXED_POINT": "Oprava bodu",
  "SWEEPING_ROBOT_MODE_FRAME": "Rám",
  "SWEEPING_ROBOT_MODE_POWER": "Nabíjanie",
  "SWEEPING_ROBOT_MODE_STRONG": "Silný",
  "SWEEPING_ROBOT_MODE_ENERGY": "Nízka energia",
  "SWEEPING_ROBOT_MODE_MINUTES": "minúty",
  "SWEEPING_ROBOT_MODE_DARK": "Šero",
  "SWEEPING_ROBOT_MODE_LIGHT": "Svetlo",
  "SWEEPING_ROBOT_MODE_NO_POWER": "Nízky výkon",
  "SWEEPING_ROBOT_MODE_STANDBY": "Pohotovostný režim",
  "SWEEPING_ROBOT_MODE_WORKING": "Pracujúci",
  "SWEEPING_ROBOT_MODE_POWER_OFF": "Vypnúť",
  "SWEEPING_ROBOT_MODE_QUIET": "Stlmiť zvuk",
  "SWEEPING_ROBOT_MODE_NORMAL": "Normálne",
  "SWEEPING_ROBOT_MODE_LOW": "Bass",
  "SWEEPING_ROBOT_MODE_STATUS": "Aktuálny stav",
  "SWEEPING_ROBOT_MODE_MODE": "Aktuálny režim",
  "SWEEPING_ROBOT_MODE_RECHARGE_TIME": "Čas nabíjania",
  "SWEEPING_ROBOT_MODE_COLOR": "Farba",
  "SWEEPING_ROBOT_MODE_GO_ON": "hore",
  "SWEEPING_ROBOT_MODE_TURN_LEFT": "vľavo",
  "SWEEPING_ROBOT_MODE_TURN_RIGHT": "vpravo",
  "SWEEPING_ROBOT_MODE_GO_BACK": "dole",
  "SWEEPING_ROBOT_MODE_ELECTRICITY": "Elektrina",
  "SWEEPING_ROBOT_MODE_VOICE": "Hlas",
  "SWEEPING_ROBOT_MODE_ERROR_FRAME": "Chyba čistenia rámu",
  "SWEEPING_ROBOT_MODE_ERROR_SCROLL": "Vyčistiť chybu pri rolovaní",
  "SWEEPING_ROBOT_MODE_ERROR_LEFT": "Chyba ľavého kolesa",
  "SWEEPING_ROBOT_MODE_ERROR_RIGHT": "Chyba pravého kolesa",
  "SWEEPING_ROBOT_MODE_ERROR_ALL_WHEEL": "Chyba všetkých kolies",
  "SWEEPING_ROBOT_MODE_ERROR_DUSK_BOX": "Chyba krabice",
  "SWEEPING_ROBOT_MODE_ERROR_SENSOR": "Chyba snímača",
  "SWEEPING_ROBOT_MODE_ERROR_CANT_CHARGE": "Chyba nedokáže nabíjať",
  "DEVICE_NAME_SINGLE_DEVICE": "Jednokanálové zariadenie",
  "DEVICE_NAME_MULTI_DEVICE": "Viackanálové zariadenie",
  "no_permission_try_system": "Potrebujete oprávnenie.",
  "realplay_loading": "Načítavam ...",
  "auto_wifi_add_device_failed": "Zlyhalo, prosím zopakujte",
  "add_device_fail": "Pridať zariadenie zlyhalo",
  "am": "a.m.",
  "pm": "p.m.",
  "cloud": "Cloud storage",
  "detail_modify_fail": "Modifikácia zlyhala",
  "pair_failure_reason_check_assistant_ios": "Skontrolujte pripojenie WiFi a uistite sa, že aplikácia sa pripája so stabilným WiFi.",
  "LOCAL_SERVER_NETWORK_CONNECTED_DEVICE": "Úspešné pripojenie zariadenia %1$s cez LAN",
  "LOCAL_SERVER_NETWORK_STATUS_CHANGE": "Sieť sa zmenila, LAN sieť sa automaticky ukončila",
  "UDP_LOCAL_NETWORK_BTN_TEXT": "Povoliť LAN",
  "UDP_LOCAL_NETWORK_BTN_CLOSE_TEXT": "Ukončiť LAN",
  "UDP_LOCAL_NETWORK_TEXT": "LAN",
  "UDP_LOCAL_NETWORK_NO_TIMER_TEXT": "V sieti LAN sa táto funkcia nesmie používať",
  "LAN_HELP_DIALOG_SUPPORT_I_KNOWN": "Mám to",
  "LAN_HELP_DIALOG_DESC": "Keď sa vaše inteligentné zariadenie a smartphone pripájajú k rovnakej sieti, môžete použiť LAN (lokálnu sieť) na pridanie a ovládanie inteligentného zariadenia.",
  "LAN_HELP_DIALOG_SUPPORT_DEVICE_TITLE": "Len niektoré z prepínačov a zásuviek podporujú LAN v najnovšej verzii aplikácie.",
  "ez_input_device_verify_code": "Prosím, zadajte autentifikačný kód zariadenia",
  "ez_input_verify_code_alert": "Vaše video bolo zašifrované, prosím, pre prezeranie vložte heslo.Pôvodné heslo je verifikačný kód z modelu štítku.Ak tam nie je štítok, zadajte ABCDEF (citlivé na veľkosť písma).",
  "ez_long_press_talk": "Stlačte a podržte hovor",
  "ez_edit": "Upraviť",
  "ez_motion_alarm": "Alarm detekcie pohybu",
  "ez_from": "Zdroj",
  "ez_no_more": "No more",
  "ez_7_days": "Správa môže byť uložená až na 7 dní",
  "ez_tag_read": "Nastaviť ako prečítané",
  "ez_delete_alarm_date": "Odstrániť tento záznam?",
  "ez_delete_alarm_success": "Úspešne odstránený",
  "ez_delete_alarm_failed": "Nepodarilo sa odstrániť",
  "ez_msg_record": "Video správy",
  "qr_scan_no_permission": "Váš fotoaparát nemá povolenie, nemôžete používať funkciu skenovania kódov QR. Prejdite na správu systémových práv, aby ste povolili povolenie.",
  "no_permission": "Nemáte povolenie, nemôžete pokračovať.",
  "youqiao_has_no_100_day_data": "Žiadna história",
  "youqiao_history_download_failure": "Stiahnutie sa nepodarilo, skontrolujte stav pamäťovej karty",
  "INSTALL_GOOGLE_PLAY_FIRST": "Nainštalujte si Google Play",
  "APP_IS_DOWNLOADING": "Aplikácia sa sťahuje",
  "has_not_location_permission": "Nepodarilo sa spárovať zariadenie. Povolenie prístupu k polohe pre aplikáciu.",
  "has_not_location_service": "Nepodarilo sa spárovať zariadenie.Povolte službu určovania polohy.",
  "NO_FEEDBACK_CONTENT": "Spätná väzba zlyhala, vložte prosím obsah",
  "DATA_EXCEPTION": "Výnimka na údaje, skúste to znova neskôr",
  "Warm": "Teplý",
  "Wet": "Vlhký",
  "Please_turn_on_the_device_switch": "Najskôr zapnite zariadenie",
  "HumidityMode": "Konštantná vlhkosť",
  "HumidityControl": "Nastavenie vlhkosti",
  "SERVER_PRIVACY": "Zmluva o poskytovaní služieb a pravidlá ochrany osobných údajov",
  "PRIVACY_CONTENT": "Vážení užívatelia, vitajte v eWeLink alikácii. Keď používate naše služby, dôverujete nám s vašimi informáciami. \n\n Predávame vám našu zmluvu o poskytovaní služieb a zásady ochrany osobných údajov, ktoré vám pomôžu pochopiť, aké informácie zhromažďujeme, prečo ich zhromažďujeme a ako chránime vaše informácie. \n\n Prosím, prečítajte si ju pozorne a uistite sa, že jej rozumiete.",
  "READ_DOC_AND_CONTINUE": "ČÍTAŤ",
  "POLICY_MAIN_WELCOME": "Vitajte na palube!",
  "POLICY_MAIN_1": "Takže ste si zakúpili náš hardvér zariadenia eWeLink a začínate používať softvér zariadenia eWeLink a všetky jeho funkcie! Akékoľvek informácie, ktoré zdieľate s nami (napríklad pre vytvorenie účtu eWeLink) nám pomôžu poskytnúť vám služby týkajúce sa do eWeLink zariadenia a zlepšiť ich, aby sme ich ešte lepšie Vysvetľujeme tu naše spôsoby zhromažďovania a používania informácií a ako chránime vaše súkromie.V týchto zásadách ochrany osobných údajov osobné údaje znamenajú informácie, ktoré možno použiť na identifikáciu jednotlivca , a to buď len z týchto informácií alebo z týchto informácií a ďalších informácií, ku ktorým máme k tejto osobe prístup, zhromažďujeme osobné aj neosobné údaje, aby sme umožnili a uľahčili čo najlepšiu používateľskú skúsenosť.\n",
  "POLICY_MAIN_2": "Pravidlá ochrany osobných údajov pravidelne kontrolujeme. Ak zmeníme naše pravidlá ochrany osobných údajov, zverejníme zmeny na všetkých webových stránkach eWeLink, aby ste si boli vedomí informácií, ktoré zhromažďujeme a ako ich používame. zmeny v našich pravidlách ochrany osobných údajov sa budú uplatňovať od chvíle, kedy ich uverejníme na webových stránkach eWeLink. Vaše pokračujúce používanie produktov a služieb na webových stránkach, mobilných telefónoch a / alebo iných zariadeniach bude považované za prijatie aktualizovaných zásad ochrany osobných údajov. Snažíme sa získať nový súhlas predtým, ako od vás zhromažďujeme viac osobných údajov, alebo ak chceme používať alebo zverejňovať vaše osobné údaje na nové účely. \n",
  "POLICY_ITEM_1": "\n 1.ZBER INFORMÁCIÍ \n\n Naša zbierka informácií bude založená na vašej interakcii s nami a na voľbách, ktoré ste urobili, vrátane nastavení ochrany osobných údajov a produktov a funkcií, ktoré používate. môžete použiť verziu SDK / API / JS, verziu softvéru, prehliadač, poskytovateľa internetových služieb (ISP), adresu IP, platformu, časovú značku, identifikátor aplikácie, verziu aplikačného programu, distribučný kanál aplikácií, Identifikátor inzerentov Android, MAC adresa, medzinárodná identifikácia mobilného zariadenia (IMEI), model zariadenia, výrobca terminálu, verzia operačného systému terminálu, začiatok / čas relácie, umiestnenie jazyka, časové pásmo a stav siete (napríklad Wi-Fi). ako aj používanie pevného disku, CPU a batérie Osobné údaje zhromaždené na vytvorenie účtu eWeLink môžu zahŕňať vašu e-mailovú adresu alebo číslo mobilného telefónu, informácie týkajúce sa zariadenia (napr. číslo IMEI ) a rôzne informácie týkajúce sa polohy (napr. kód oblasti lokality, kód mobilnej siete a kód krajiny). \n\nV priebehu nasledujúcich procedúr môžeme zhromažďovať informácie \n\n · Nastaviť a prihlásiť sa do účtu eWeLink. Osobné údaje zhromaždené na vytvorenie účtu eWeLink môžu zahŕňať vašu e-mailovú adresu alebo číslo mobilného telefónu, informácie týkajúce sa zariadenia (napr. Číslo IMEI) a rôzne informácie týkajúce sa polohy (napr. Kód oblasti polôh, kód mobilnej siete a krajiny). · Zakúpenie produktov eWeLink. Ak nakupujete prostredníctvom webovej lokality elektronického obchodovania eWeLink, môžeme získať e-mailové konto eWeLink (alebo číslo mobilného telefónu alebo e-mailovej adresy použité na vytvorenie účtu eWeLink), meno, telefónne číslo, adresu doručenia, podrobnosti objednávky atď. logistické služby na dodanie produktov zakúpených na internetovej stránke elektronického obchodu. Systém eWeLink má systém popredajného predaja, ktorý sa zaoberá záležitosťami po predaji, ako aj popredajné centrum pre služby zákazníkom. Keď použijete tieto služby, môžeme tiež získať číslo objednávky, dátum faktúry, zoznam zakúpených položiek a kontaktné údaje, aby sme spracovali tieto služby. \n\n · Spätná väzba od používateľov. Keď odosielate spätnú väzbu používateľov prostredníctvom aplikácie eWeLink, môžeme zhromažďovať informácie o zozname zariadení registrovaných vo vašom účte, ako aj o súvisiacich informáciách o prevádzke zariadenia a informáciách o zariadení. \n\n · Synchronizácia údajov zariadenia eWeLink. Keď synchronizujete dáta zariadenia eWeLink, napr. na zariadenie eWeLink Cloud Service môžeme zhromažďovať údaje týkajúce sa vašich aktivít a funkcií zariadenia eWeLink, ako sú tie, ktoré sme získali z našich senzorov a funkcií v zariadení eWeLink, spánkových modeloch, údajoch o pohybe a informáciách týkajúcich sa inteligentného alarmu. \n\n Spracovanie služieb. Pri poskytovaní vyššie uvedených služieb môžeme tiež zhromažďovať údaje vo vzťahu k vášmu zariadeniu, vrátane ID vášho zariadenia eWeLink, verzie firmvéru, verzie operačného systému, modelu a systému a návštevy IP a času. ",
  "POLICY_ITEM_2": "\n 2.POUŽITIE OSOBNÝCH ÚDAJOV \n\n Slúžia na zlepšenie produktov.Používame údaje na neustále zlepšovanie našich produktov vrátane pridávania nových funkcií a zvyšovania kapacity Napríklad: \n\n · Poskytovanie našich produktov spracovanie objednávok, plnenie zmluvných záväzkov medzi vami a nami, zabezpečenie funkcií a bezpečnosti našich produktov, overovanie vašej identity, predchádzanie a sledovanie podvodného alebo nevhodného používania \n\n · vývoj našich produktov a služieb, spolu s všeobecnými a štatistickými informáciami. \n\n · komunikovať s vami, vrátane poskytovania upozornení na produkty a služby, ktoré sú aktualizované alebo spustené; \n\n · poskytovať vám marketingové a propagačné materiály o našich produktoch a službách (prosím poznamenať, že sa môžete kedykoľvek odhlásiť) \n\n · Prispôsobiť si dizajn produktu a poskytnúť vám služby, ktoré sú na mieru prispôsobené napríklad vám odporúčajú a zobrazujú informácie a inzeráty týkajúce sa produktov, ktoré vám vyhovujú, a pozývam vás, aby ste sa zúčastnili prieskumov týkajúcich sa vášho používania zariadenia eWeLink. \n\n · Vykonať vyšetrovanie týkajúce sa našich produktov a služieb. \n\n · Ak sa zúčastňujete našej lotérie, súťaže alebo iných propagačných akcií, môžeme použiť vaše osobné údaje na riadenie týchto aktivít \n\n · Poskytovať služby údržby, monitorovať softvérové ​​licencie, zlepšovať naše produkty alebo analyzovať efektivitu našich operácií. \n\n Ak používate naše služby alebo funkcie založené na informáciách o polohe, napr. pri pridávaní zariadení eWeLink môžeme zhromaždiť vaše geografické informácie. \n\n · Keď používate našu webovú stránku, online služby, interaktívne aplikácie, e-mailové správy a reklamu, môžeme na zhromažďovanie a ukladanie súborov cookie a iných technických prvkov (napr. neosobné údaje. To nám umožňuje poskytnúť vám lepšie skúsenosti a zlepšiť našu celkovú kvalitu služieb, napr. pri ukladaní predvolených nastavení jazyka, odosielaní e-mailov v čitateľnom formáte, pri určovaní, či boli e-maily otvorené alebo nie, atď. \n\n · Keď používate internetový prehliadač pri používaní našich produktov a služieb, , napr IP adresa, typ prehliadača, jazyk, referenčný zdroj, operačný systém, označenie dátumu a času a údaje o rýchlosti kliknutia. ",
  "POLICY_ITEM_3": "\n 3.ZDIELANIE OSOBNÝCH ÚDAJOV \n\n  Ak chcete naše produkty lepšie vylepšiť, môžeme zdieľať vaše osobné údaje s našimi poskytovateľmi služieb alebo agentmi na účely uvedené v týchto pravidlách. poskytovateľ môže zhromažďovať a pristupovať k osobným údajom pre štatistiky a analýzy.V tomto kontexte musia tieto spoločnosti spĺňať naše požiadavky na ochranu osobných údajov a bezpečnosti. \n\n Kto s nami zdieľame vaše informácie? \n\n Ak sme vám v týchto pravidlách ochrany osobných údajov , budeme vaše osobné údaje uchovávať ako dôverné.Možno osobné údaje zverejniť tretím stranám s cieľom poskytnúť požadované produkty alebo služby.Niektoré z týchto tretích strán môžu byť umiestnené mimo vašej domovskej krajiny. \n\n Disclosure môže obsahovať scenáre uvedené nižšie V každom prípade popísanom v tejto časti môžete byť istí, že eWeLink bude zdieľať vaše osobné údaje iba s vaším súhlasom.Mali by ste vedieť, že keď eWeLink sh vaše osobné údaje s treťou stranou za akýchkoľvek okolností opísaných v tejto časti, eWeLink zabezpečí, aby tretia strana podliehala postupom a povinnostiam dodržiavať príslušné zákony o ochrane údajov a súkromia vašej krajiny. Spoločnosť eWeLink zmluvne zabezpečí dodržiavanie pravidiel ochrany osobných údajov, ktoré platia vo vašej domácej jurisdikcii, akýmkoľvek zahraničným poskytovateľom služieb tretej strany. \n\n Distribúcia spoločnostiam skupiny eWeLink a poskytovateľom služieb tretích strán \n\n  · Aby bolo možné bezproblémovo vykonávať obchodné operácie Spoločnosť eWeLink, ktorá zhromažďuje vaše osobné údaje, môže z času na čas zverejniť vaše osobné údaje iným spoločnostiam skupiny eWeLink (v oblasti komunikácie, sociálnych médií, technológií alebo cloud computingu) alebo tretím poskytovateľom služieb, ktorými sú naše poštové domy, telekomunikačné spoločnosti, dátové centrá, zariadenia na ukladanie údajov a poskytovateľov služieb zákazníkom, agentov, prepojených spoločností a / alebo iných tretích strán (spoločne \"Poskytovatelia služieb tretích strán\"). Takíto poskytovatelia tretích strán by spracúvali vaše osobné údaje v mene eWeLink alebo pre jeden alebo viac z vyššie uvedených účelov. \n\n  · Osobné údaje budú zdieľať iba eWeLink na poskytovanie alebo vylepšenie našich produktov alebo služieb a nebudú zdieľané na použitie na marketingové účely. \n\n Distribúcia na iné osoby \n\n eWeLink môže zverejniť vaše osobné údaje bez ďalšieho súhlasu, ak to vyžaduje alebo je povolené zákonom v nasledujúcich prípadoch: \n\n  · prípady, na základe platných zákonov a / alebo nariadení; \n\n  · prípady, v ktorých je zverejnenie nevyhnutné na to, aby reagovalo na núdzové situácie ohrozujúce život, zdravie alebo bezpečnosť jednotlivca alebo inej osoby; zverejnenie je nevyhnutné na predchádzanie trestnej činnosti alebo súdnemu konaniu; \n\n  · prípady, v ktorých je účel takéhoto zverejnenia jednoznačne v záujme jednotlivca a ak nie je možné získať súhlas včas; \n\n  · prípady v ktorých je zverejnenie nevyhnutné ktoré sa týkajú akéhokoľvek vyšetrovania alebo konania; \n\n  · v prípadoch, keď je zverejnenie adresované akémukoľvek úradníkovi predpísanej represívnej agentúry po predložení písomného splnomocnenia podpísaného vedúcim alebo riaditeľom tejto agentúry na presadzovanie práva alebo osobou podobnej že osobné údaje sú potrebné na účely funkcií alebo povinností dôstojníka; a / alebo \n\n  · prípady, keď je zverejnenie určené verejnej agentúre a takéto zverejnenie je nevyhnutné vo verejnom záujme. \n\n Informácie, ktoré nevyžadujú súhlas \n\n  • Môžeme zdieľať anonymizované informácie a štatistiky v agregovanej podobe s tretími stranami na obchodné účely, napríklad s inzerentmi na našej webovej stránke, alebo môžeme informovať našich obchodných partnerov o počte zákazníkov v určitých demografických skupinách, ktorí kúpili určité produkty alebo vykonali určité transakcie. \n\n  • Aby ste zabránili pochybnosti, v prípade, že sme zo zákona oprávnení zbierať, používať alebo zverejňovať vaše osobné údaje bez vášho súhlasu, takéto povolenie udelené zákonom sa naďalej uplatňuje. ",
  "POLICY_ITEM_4": "\n 4.PRÁVNY ZÁKLAD PRE SPRACOVANIE DÁT \n\n Poznámili sme sa na účely spracovania osobných údajov, ktorých právnym základom je: vykonanie zmluvy medzi vami a eWeLinkom (napr. Poskytnutie služieb požiadali ste, aby ste vykonali identifikáciu a overovanie, aby ste mohli používať našu webovú stránku), dodržiavať zákonné požiadavky (napr. dodržiavať platné účtovné pravidlá, splniť požiadavku povinného odhalenia od orgánov činných v trestnom konaní), chrániť naše oprávnené záujmy (napr. riadiť náš vzťah s vami, zabezpečiť bezpečnosť našich služieb, komunikovať s vami o našich produktoch a službách) a stavať na súhlase našich klientov (napr. používať cookies, zdieľať vaše informácie s tretie strany na účely reklamy). \n\n V niektorých prípadoch možno budete musieť poskytnúť nám vaše osobné údaje na vyššie uvedené účely, aby sme mohli ponúknuť celý rad služieb a uľahčiť využívanie všetkých funkcií na našich webových stránkach. ",
  "POLICY_ITEM_5": "\n 5.MEDZINÁRODNÉ PREVODY OSOBNÝCH ÚDAJOV\n\n Naša spoločnosť môže požiadať o prenos osobných údajov do krajín mimo Európskeho hospodárskeho priestoru vrátane Číny alebo Singapúru. Musia sa prijať príslušné opatrenia, aby sa zabezpečilo, že prijímatelia vašich osobných údajov údaje sa držia záväzkov týkajúcich sa ich dôvernosti a zabezpečujeme, aby sme vykonali opatrenia, ako sú štandardné zmluvné podmienky. Informácie o týchto podmienkach získate od nášho centra podpory.",
  "POLICY_ITEM_6": "\n 6.VAŠE PRÁVA\n\n Podľa platných zákonov máte právo vzniesť námietku proti obmedzeniu spracovania vašich osobných údajov alebo požiadať o obmedzenia a požiadať o prístup, opravu, vymazanie a prenosnosť vašich údajov .\n\n Môžeme vaše údaje používať len na základe vášho súhlasu.Máte právo kedykoľvek odstúpiť od vášho súhlasu, avšak nemá vplyv na oprávnenosť spracovania údajov, ktoré sme získali s vaším súhlasom, .\n\n Môžete požiadať o zrušenie účtu alebo o odobratí súhlasu s pravidlami ochrany osobných údajov v používateľskom centre v našej aplikácii.\n\n Môžete tiež poslať e-mail na adresu app@coolkit.cn, kde môžete požiadať o spracovanie osobných údajov \n\nV prípade, že zistíte zmeny alebo nepresnosti vo vašich informáciách, informujte nás o zmenách, aby sme mohli aktualizovať alebo opraviť záznamy.Ak zistíte, že naše praktiky vo vzťahu k vašim osobným údajom porušili určité platné zákony, máte právo na podanie sťažnosti ts regulačnému orgánu. \n\nDĺžka trvania uchovávania údajov bude určená službami alebo produktmi, o ktoré ste požiadali, alebo ustanoveniami alebo schválením platných zákonov, napríklad daňového práva a účtovného práva. ",
  "POLICY_ITEM_7": "\n 7.INFORMAČNÉ BEZPEČNOSTNÉ ZÁRUKY \n\n Naša spoločnosť sme sa zaviazali zabezpečiť bezpečnosť vašich osobných údajov.Aby sme zabránili neoprávnenému prístupu, zverejneniu alebo iným podobným rizikám, zaviedli sme primerané fyzické, elektronické a manažérske postupov na zabezpečenie a zabezpečenie informácií, ktoré zhromažďujeme .. Zaviedli sme nasledujúce bezpečnostné postupy a technické a organizačné opatrenia na ochranu vašich osobných údajov: \n\n · Vaše osobné údaje sú uložené na zabezpečených serveroch, ktoré sú chránené v kontrolovaných zariadeniach. \n\n · Všetky dáta uložené v back-end sa rozdeľujú na rôzne úrovne založené na dôležitosti a citlivosti údajov, napr. či údaje obsahujú osobné údaje. \n\n · V dátových centrách sú klastre, ktoré obsahujú citlivé údaje sú zoskupené do topológie siete a budú umiestnené v miestnostiach s dodatočnou ochranou fyzického zabezpečenia. \n\n · Dáta vymieňané medzi zariadeniami eWeLink a servermi sú šifrované pomocou Secure Sockets La yer (\"SSL\"). \n\n · Keď používatelia pristupujú k svojmu účtu eWeLink, existuje voliteľný dvojstupňový proces overenia. \n\n Pravidelne sa skúmajú postupy zberu, ukladania a spracovania informácií vrátane fyzických bezpečnostných opatrení , aby sa zabránilo neoprávnenému prístupu k systémom. \n\n Prístup je obmedzený na zamestnancov eWeLink a poskytovateľov služieb tretích strán, ktorí potrebujú poznať tieto informácie na spracovanie a ktorí podliehajú prísnym zmluvným záväzkom mlčanlivosti a môžu byť disciplinovaní alebo sa ukončia, ak nesplnia takéto povinnosti. \n\n · Existujú aj prístupové ovládacie prvky pre všetky serverové klastre používané na ukladanie a spracovanie dát v cloude. \n\n · Väčšina údajov použitých pre produkty a / alebo služby eWeLink je uložené v pamäťovom systéme. Pomocou mechanizmu na riadenie prístupu založeného na stĺpcoch umožňujú zamestnancom systému eWeLink prístup iba k rodinám s dátovými stĺpmi, ktorým im bol udelený prístup. \n\n · Upozorňujeme tiež, že eWeLink môže v súvislosti s vyššie uvedeným využívať zariadenia v zahraničí, ktoré prevádzkuje a riadi eWeLink spracovávať alebo zálohovať osobné údaje. V súčasnosti má eWeLink dátové centrá v Pekingu a Singapure. V dôsledku toho môžeme preniesť a uchovávať vaše osobné údaje v našich zahraničných zariadeniach. To však nezmení žiaden z našich záväzkov chrániť vaše osobné údaje v súlade s týmito Zásadami ochrany osobných údajov. \n\nInformačná bezpečnosť je pre nás veľmi dôležitá. Vykonáme všetky praktické kroky na ochranu vašich osobných údajov. Prostredníctvom našich vyššie uvedených ochranných opatrení, najmä šifrovaného ukladania a prenosu, sú vaše dáta tak bezpečné, ako to môže byť. Niektoré podrobnosti o zašifrovaných údajoch nemôžu byť prístupné nikomu okrem vás. ",
  "EWELINK_ACCOUNT": "účet eWeLink",
  "CANCEL_AUTH": "Zrušiť autorizáciu",
  "CANCEL_AUTH_CANT_USE_APP": "Po zrušení autorizácie nemôžete používať služby eWeLink, naozaj chcete zrušiť?",
  "Sleep": "Režim spánku",
  "ChildLock": "Detský zámok",
  "Need_to_replace_filter": "Nutnosť nahradiť filter",
  "Whether_to_open_child_lock": "Či chcete otvoriť detský zámok?",
  "INPUT_CURRENT_ACCOUNT": "Prosím, zadajte aktuálny účet",
  "ONLY_CAN_LOGOUT_CURRENT_ACCOUNT": "Môžete odstrániť iba bežný účet",
  "LOGOUT_ACCOUNT": "Odstrániť účet",
  "LOG_OUT_TEXT": "Áno",
  "LOGOUT_ACCOUNT_FAILED": "Účet sa nepodarilo odstrániť",
  "GET_LOGOUT_EWELINK_ACCOUNT": "Odstrániť účet eWeLink",
  "LOG_OUT_ACCOUNT_SUCCESS": "Váš účet bol odstránený",
  "APPLY_FOR_CANCELLATION": "Odstrániť účet",
  "PRIVACY_POLICY": "Zásady ochrany osobných údajov",
  "GIVE_UP_USE": "Zrušiť",
  "AGREE_AND_USE": "Súhlasím a pokračujte",
  "REMIND": "POZNÁMKA",
  "INPUT_YOU_WANT_CANCELLATION": "Zadajte účet, ktorý chcete odstrániť",
  "HAS_READ_TOP_CONTENT": "Súhlasím",
  "GET_VERIFICATION_CODE": "Overovací kód",
  "PLEASE_INPUT_VERIFICATION_CODE": "Zadajte verifikačný kód tu",
  "CANCELLATION_TEXT1": "Chystáte sa vymazať účet eWeLink.Pre bezpečnosť účtu si prosím pozorne prečítajte tieto informácie:",
  "CANCELLATION_TEXT2": ": Po vymazaní budú všetky súvisiace údaje vymazané. Nebudete môcť používať služby eWeLink vrátane, ale nie výhradne, prístupu k informáciám o zariadení, používaní funkcií zariadenia, ako je scéna a skupina, ovládanie zariadenia s aplikáciou eWeLink alebo platformami tretích strán, ako je doma Google, Amazon Alexa, IFTTT a WeChat. ",
  "CANCELLATION_AND_CANT_USE_EWELINK": "Po odstránení nemôžete používať služby eWeLink. Naozaj chcete odstrániť účet teraz?",
  "SURE_TOP_TO_LOG_OUT": "Prosím začiarknite \"Súhlasím\" a pokračujte!",
  "HAS_SPACE_ON_TEXT": "Zadaný účet obsahuje znak medzery, skontrolujte a znova zadajte!",
  "Nature": "Natural",
  "Fan_switch": "Spínač ventilátora",
  "Lamp_switch": "Spínač svetiel",
  "Added_successfully": "Pridaná úspešne",
  "The_device_is_connecting_to_WIFI__please_wait": "Zariadenie sa pripája k službe WIFI, môže trvať niekoľko minút, čakajte ...",
  "DEVICE_UPGRADE": "Aktualizácia firmvéru",
  "ENTER_PHONE_OR_EMAIL": "Zadajte svoje telefónne číslo alebo e-mail",
  "describ_feebback": "Popíšte svoju spätnú väzbu tu",
  "ISSUE_TYPE": "typ problému",
  "TIPS": "Tipy",
  "OTHER": "Ostatné",
  "SettingTemperature": "Nastavenie teploty",
  "SettingUnit": "Nastavovacia jednotka",
  "Ozone": "Ozón",
  "Trying_to_connect_the_device": "Pokúšať sa pripojiť zariadenie",
  "Current_gear": "Aktuálná rychlosť",
  "SURE_CHANGE_TO": "Naozaj sa chcete prepnúť na",
  "SCENE_ADD_SERSOR_CONDITION_VALUE": "Zadajte číslo",
  "SELECT_ISSUE_TYPE": "Vyberte typ vydania",
  "TMALL_ISSUE": "TmallGenie",
  "GOOGLE_HOME_ISSUE": "Domovská stránka Google",
  "VERIFY_CODE_ISSUE": "Overovací kód",
  "LOGIN_ISSUE": "Prihlásiť sa",
  "TIMER_ISSUE": "Časovač",
  "OTHER_DEVICE_ISSUE": "Iné",
  "ADD_DEVICE_ISSUE": "Pridávanie zariadení",
  "SELECT_COMMON_ISSUE": "Problém, ktorý ste vybrali, je bežný problém. Pozrite si časté otázky",
  "MEARIKIT_CAMERA_NAME": "Kamera Mearikit",
  "QRCODE_SCAN_IMAGE_TEXT": "Zarovnanie QR kódu v rámci snímania",
  "NO_SHARE_DESC_TEXT": "Klepnutím tu zdieľajte",
  "SCENE_INTER_LOG_NULL_DATA": "Nemáte žiadne záznamy o prevádzke",
  "The_air_temperature": "Teplota vzduchu",
  "Lighting_effects": "Svetlo",
  "Effect_of_noise": "Hluk",
  "Humidity_of_the_air": "Vlhkosť vzduchu",
  "SPEED_1": "1",
  "SPEED_2": "2",
  "SPEED_3": "3",
  "SLEEP_MODE_CANT_CHANGE_GEAR": "V režime spánku nie je povolené prepínanie na iný režim,",
  "NATURE_MODE_CANT_CHANGE_GEAR": "V prirodzenom režime nie je povolené prepínanie na iný režim",
  "INPUT_YOUR_NEW_NICKNAME": "Nová prezývka",
  "CAMERA_VIDEO_LEVEL_SUPERHIGH": "Super Definícia",
  "MORE_THAN_20_GROUP": "Môžete nastaviť maximálne 20 skupín!",
  "nest_tempec_limit": "Aktuálny teplotný rozsah: -50 ~ 150 ° C",
  "nest_tempef_limit": "Aktuálny rozsah teplôt: -122 ~ 302 ℉",
  "nest_target_tempec_limit": "Cieľový rozsah teplôt: -50 ~ 150 ° C",
  "nest_target_tempef_limit": "Cieľový rozsah teplôt: -122 ~ 302 ℉",
  "CAMERA_NOT_SUPPORT_TALKING": "Toto zariadenie nepodporuje tlmočenie",
  "CLEAN_ONE_KEY": "Vymazať celú históriu",
  "SHARE_ADD_DIALOG_TITLE": "Ovládanie zdieľania",
  "TIMER_ADD_OR_UPDATE_YEAR_SELECT": "Rok",
  "SCENE_CONDITION_TEMPRETURE_IS_SAME": "Udržujte konzistentnú jednotku temp",
  "CAMERA_PLAY_NO_PERMISSION": "Odmietli ste požadované povolenia a nemôžete zobraziť fotoaparát",
  "CAMERA_ADD_NO_PERMISSION": "Odmietli ste požadované povolenia a zariadenie typu fotoaparátu nemôžete pridať",
  "CONTROL_PTZ_FAILED": "Nepodarilo sa ovládať PTZ",
  "SET_VIDEO_LEVEL_FAILED": "Nepodarilo sa nastaviť kvalitu",
  "MIN_POWER": "Min výkon",
  "MAX_POWER": "Maximálny výkon",
  "PERFORM_SECOND": "Akcia:",
  "PERFORM_ONCE": "Spustiť činnosť:",
  "REMOVE_REMOTE_DEVICE": "Po odstránení vzdialeného zariadenia nemôžete v aplikácii ovládať príbuzné zariadenia a všetky súvisiace scény budú vymazané Pokračovať?",
  "RF_BRIDGE_NO_HAS_REMOTE_1": "RF Bridge nemáte žiadne Remotes",
  "RF_BRIDGE_NO_HAS_REMOTE_2": "Klepnutím tu pridajte vzdialené",
  "RF_BRIDGE_ALARM_HISTORY": "História alarmov",
  "The_device_is_connecting_to_GSM__please_wait": "Vaše zariadenie sa pripája do siete, môže trvať až niekoľko minút, čakajte ...",
  "YEAR_TEXT": "rok",
  "HOUR_TEXT": "Hodina",
  "SCENE_LIST_SECTION_NORMAL_TITLE": "Manuálne",
  "SCENE_LIST_SECTION_INTER_TITLE": "Auto",
  "GROUP_EDIT": "Upraviť",
  "GROUP_REMOVE_DEVICE_OF_GROUP": "Naozaj chcete odstrániť toto zariadenie zo skupiny?",
  "GROUP_REMOVE_DEVICE_OF_GROUP_TITLE": "Odstránené",
  "SCENE_ADD_CONDITION_TEXT": "Pridať",
  "SCENE_ADD_IMMEDIATE_EXECUTION": "Spustiť teraz",
  "SCENE_ADD_CONDITION_HEAD_TITLE": "Ak",
  "WHEN_MEET": "Stav",
  "MINUTE_LOWERCASE": "min",
  "duration_cycle": "Cyklus:",
  "LOGOUT_APP_ALERT": "Po odhlásení nebudú vymazané žiadne údaje z histórie, tento účet môžete použiť na ďalšie prihlásenie.",
  "END_TIME": "Koniec času",
  "VIDEO_RESOURCE_EMPTY": "Toto video nebolo nájdené",
  "ALL_ON": "Všetky kanály ON",
  "ALL_OFF": "Všetky kanály OFF",
  "FAN_CONTROL": "Ovládanie ventilátora",
  "CYCLE_TIMER_LIMIT_3": "Support to set max 24 hours countdown time.",
  "DURATION_TION_RUN_AT": "Start at:",
  "DELAY_RESET_TIMER_BTN": "Reset",
  "DELAY_RESET_TIMER_SUCCESS": "Time reset successfully.",
  "AFTER_THIS_TIME_TO_PERFORM_ACTION": "Countdown at:",
  "AFTER_THIS_TIME_TO_PERFORM_ACTION_ENABLE": "Enable and countdown at:",
  "NO_TIMER_PERMISSIONS_ADD": "You do not have permission to add timer. Contact the device owner to obtain permission.",
  "NO_TIMER_PERMISSIONS_EDIT": "You do not have permission to modify timer. Contact the device owner to obtain permission.",
  "NO_TIMER_PERMISSIONS_DELETE": "You do not have permission to delete timer. Contact the device owner to obtain permission.",
  "NO_TIMER_PERMISSIONS_enable_and_disable": "You do not have permission to enable or disable timer. Contact the device owner to obtain permission.",
  "MACHINE_BED_LIST_MASSAGE_MODE": "massage mode",
  "MACHINE_BED_LIST_MASSAGE_MODE_1": "gentle",
  "MACHINE_BED_LIST_MASSAGE_MODE_2": "comfortable",
  "MACHINE_BED_LIST_MASSAGE_MODE_3": "relaxing",
  "Stopped": "Stopped",
  "Hide_full_on_full_off_button": "Disable to turn on/off all channels",
  "RF_BRIDGE_WARNING_NOTICE": "Alarm Notification",
  "CURRENT_NETWbuORK_NOT_USABLE": "Network Error. Please check your network connection and try again!",
  "get_wifi_name_fail_request_location_try_again": "WiFi SSID restriction. Please grant the location permission to have access to your location information.",
  "not_connect_wifi_please_connect": "Not connected to the Internet. Please check your connection and try again.",
  "the_location_service_needs_to_be_opened": "eWeLink needs to turn on location services on your mobile device for permission to access your location information.",
  "SELECT_COUNTRY_PARTY": "Select your country or region",
  "Inching_function": "The inching feature",
  "input_account_share": "enter account to share with",
  "FEEDBACK_SUBOPTION_16": "Other assistants",
  "FEEDBACK_OPTION_NUM": "Account accessibility",
  "FEEDBACK_OPTION_IFTTT": "Help with Google Home/Alexa/IFTTT/Other Voice assitant",
  "FEEDBACK_OPTION_APP": "Help with eWeLink APP",
  "FEEDBACK_OPTION_BUS": "Business communication",
  "FEEDBACK_OPTION_SUG": "Feature request/Suggestion",
  "FEEDBACK_OPTION_OTHER": "Other",
  "FEEDBACK_SUBOPTION_1": "Unable to sign up",
  "FEEDBACK_SUBOPTION_2": "Unable to log in",
  "FEEDBACK_SUBOPTION_3": "Can not receive verification code",
  "FEEDBACK_SUBOPTION_4": "Forgot password",
  "FEEDBACK_SUBOPTION_5": "Google Home",
  "FEEDBACK_SUBOPTION_6": "Amazon Alexa",
  "FEEDBACK_SUBOPTION_7": "Tmall Genie",
  "FEEDBACK_SUBOPTION_8": "Google Nest",
  "FEEDBACK_SUBOPTION_9": "Unable to pair",
  "FEEDBACK_SUBOPTION_10": "Devices offline",
  "FEEDBACK_SUBOPTION_11": "Schedule/timer/Loop timer",
  "FEEDBACK_SUBOPTION_12": "Device sharing",
  "FEEDBACK_SUBOPTION_13": "Firmware upgrade",
  "FEEDBACK_SUBOPTION_14": "Scene setting",
  "FEEDBACK_SUBOPTION_15": "APP notification",
  "PREPARE_FEEDBACK_DESC": "Committed to provide you with professional, efficient, and premium smart home service. Any of Your suggestions are very valuable to us",
  "FEEDBACK_CHOOSE_DEVICE_TITLE": "Please select your device",
  "FEEDBACK_INPUT_PHONE": "Please enter your contact number",
  "FEEDBACK_INPUT_ACCOUNT": "Please enter your sharing account",
  "FEEDBACK_UPLOAD_IMAGE_TITLE": "Upload photos (optional)",
  "FEEDBACK_BUSS_DESC_TEXT": "If you want to cooperate with eWelink for business, please fill in the form below, we will contact you timely",
  "FEEDBACK_PHONE_NOT_ALLOW": "Contact number range must have at least 5 digits up to 20 digits ",
  "FEEDBACK_PERMISSION_DENIED": "This feature needs permission to read your pictures, OK?",
  "FEEDBACK_CHOOSE_IMAGE_TITLE": "Select your albums",
  "please_grant_camera_permission": "Allow eWelink to access your camera OK?",
  "not_grant_camera_permission": "Camera access permission error",
  "please_grant_storage_permission": "Allow eWelink to access your storage OK?",
  "not_grant_storage_permission": "Storage access permission error ",
  "manual": "Manual",
  "program": "Program",
  "antifreeze": "Antifreeze",
  "heat_state": "Heat state",
  "heating": "Heating",
  "program_mode": "Program mode",
  "antifreeze_mode": "Antifreeze mode",
  "time_point": "Timing",
  "time_period": "Time period",
  "add_new_time_point": "Add new timing",
  "select_time_point": "Select timing",
  "input_target_temperature": "Input targeted temperature",
  "wave_range": "Wave range",
  "restore_factory_settings": "Restore factory setting",
  "are_you_sure_restore_factory_settings": "After restoring factory mode, previous settings will be disable. Are you sure restoring factory mode?",
  "target_temperature_must_be": "( Targeted temperature must be set on a multiple of 0.5 degree)",
  "not_set": "Unset",
  "temporary_temperature": "Set temperature",
  "execute_time": "Execution time",
  "edit_time_point": "Edit timing",
  "rui_mi_te_cannot_low": "Not lower than",
  "rui_mi_te_cannot_high": "Not higher than",
  "rui_mi_te_cannot_keep_at_least_time_point": "Min. 1 timing",
  "rui_mi_te_cannot_most_set_time_point": "Max. 6 timings",
  "rui_mi_te_cannot_target_temp_must_be": "Targeted temperature must be set on a multiple of 0.5 degree（0.0 or 6.0~35.0）",
  "rui_mi_te_cannot_setting_success": "Success",
  "rui_mi_te_list_heat": "Heating",
  "EWELINK_ROUTER_NAME": "eWeLink router",
  "OPEN_BATTERY_LOCK_FAILED": "Fail to open the Battery Lock",
  "OPEN_BATTERY_LOCK": "Open the Battery Lock",
  "OPEN_BATTERY_LOCK_SUCCESS": "30 seconds after users remove batteries, the Battery Lock will lock automatically.",
  "SHE_XIANG_TOU": "Camera",
  "CHOOSE_CAMERA": "Choose the camera",
  "EWELINK_CAMERA": "eWeLink camera",
  "rolling_door_as_per_open": "Open in proportion",
  "SELECT_DEVICE_TYPE": "Choose the device",
  "MEARI_CAMERA_TYPE": "Camera",
  "MEARI_BELL_TYPE": "Smart visual doorbell",
  "MEARI_PAIR_TYPE": "Connect device to network",
  "MEARI_WIFI_PIR_MODE": "Wi-Fi connection",
  "MEARI_QRCODE_PIR": "Scan QR code",
  "MEARI_QRCODE_PIR_DES": "Scan a generated QR code by smartphone to connect",
  "MEARI_WLAN": "Wireless connection",
  "MEARI_INSTALL_DEVICE": "Device setup",
  "MEARI_WIFI_NOTICE": "Power on the device and wait for 3-10 seconds. The red status indicator light will start to blink slowly, then click “Next”.",
  "MEARI_QRCODE_NOTICE": "Power on the device, tap the re-set button and wait for 3-10 seconds. The red status indicator light will start to blink slowly, then click “Next”.",
  "MEARI_ADD_DEVICE_HELP_DOC": "The status indicator light help page",
  "MEARI_TOP_NOTICE": "Scan the QR code with your smartphone camera at a distance of 15cm or so. And don't shake the smartphone.",
  "MEARI_QRCODE_SUCCESS_ALERT": "If it's done, you'll hear a beep sound.",
  "MEARI_QRCODE_FAILED_ALERT": "If it fails, you'll resume or connect device to network again.",
  "MEARI_HAS_FIND": "has been detected",
  "MEARI_NUMBER_OF_DEVICE": "devices",
  "MEARI_WIFI_FAILED_START_QR": "No device has been detected, please try to scan the QR code to connect",
  "MEARI_HAS_ADD": "Device added",
  "MEARI_ADD": "+Add device",
  "MEARI_QR_FIND_DEVICE_ALERT": "The device has been connected to network. Please click here to go to the device list for checking device details.",
  "MEARI_SEARCH_HELP": "Help Page",
  "MEARI_DOC_TITLE1": "1、The status indicator light",
  "MEARI_DOC_CONTENT1_ITEM1": "① The red status indicator light blinks slowly: the device is ready to be connected to network.",
  "MEARI_DOC_CONTENT1_ITEM2": "② The red status indicator light blinks quickly: the device is being connected to network.",
  "MEARI_DOC_CONTENT1_ITEM3": "③ The red status indicator light is always on: network connection failed.",
  "MEARI_DOC_CONTENT1_ITEM4": "④ The blue status indicator light is always on：network connection okay.",
  "MEARI_DOC_TITLE2": "2、Fail to add device",
  "MEARI_DOC_CONTENT2_ITEM1": "① Please check if your Wi-Fi password is right or not.",
  "MEARI_DOC_CONTENT2_ITEM2": "② Please confirm your Wi-Fi router is 2.4Ghz.",
  "MEARI_DOC_CONTENT2_ITEM3": "③ Please keep your device and smartphone near the router.",
  "MEARI_DOC_TITLE3": "3、Unbind device",
  "MEARI_DOC_CONTENT3_ITEM1": "If the device needs to be added to another APP account, it has to be unbound from the original APP account first.",
  "MEARI_DOC_TITLE4": "4、Reset the device",
  "MEARI_DOC_CONTENT4_ITEM1": "When it appears network error or you need to change Wi-Fi, please press the Reset button (for about 4 seconds) until you hear an audio cue.",
  "ROLLING_DOOR_CLICK_OPEN": "Click Enable",
  "KAI_WEI_ROUTER_ONE_KEY_PAIRING_QUIT_PAIRING": "Pairing is completed",
  "FEEDBACK_USER_CALL_TEXT": "Please leave your name",
  "KAI_WEI_ROUTER_ONE_KEY_PAIRING_Fail": "This operation fails, please check if eWeLink router is connected or not",
  "KAI_WEI_ROUTER_CONNECT_Fail": "Please connect eWeLink router",
  "KAI_WEI_ROUTER": "eWeLink router",
  "MEARI_NO_STORYAGE_PERMISSION": "Unable to use QR code scan feature due to no storage permission granted. Please grant the permission first.",
  "MEARI_MOTION_CHECK": "Motion detection",
  "MEARI_PERSON_CHECK_CONTENT": "Enabling the human detection feature can monitor the behaviour of the man who is standing just outside the doorbell and give an alarm.",
  "MEARI_MOTION_CHECK_CONTENT": "Enabling the motion detection feature can monitor the behaviour of the man in front of the camera and give an alarm.",
  "MEARI_ACTION_ALERT": "Allow notification",
  "HAF_TITLE": "Help & Feedback",
  "DIAGNOSE_SUBMIT_SUCCESS": "Submitted successfully",
  "DIAGNOSE_SUBMIT_FAIL": "Fail to submit, please try again.",
  "DIAGNOSE_TITLE": "Network diagnosis",
  "DIAGNOSE_REY_AGAIN": "Diagnose again",
  "DIAGNOSE_BEGIN": "Start to diagnose",
  "DIAGNOSE_RESULT": "Diagnosis result",
  "DIAGNOSE_SUBMIT_TITLE": "Submit the diagnosis result",
  "DIAGNOSE_LOGIN_SERVER": "Login service",
  "DIAGNOSE_ALLOC_SERVER": "Distribution service",
  "DIAGNOSE_DEVICE_SERVER": "Device service",
  "KAI_WEI_ROUTER_UNBIND_ERROR_502": "Invalid operation error: the device has not yet been bound to any APP account.",
  "DIAGNOSE_SUBMIT_FAIL_DOING": "Diagnosis is not completed.",
  "DIAGNOSE_SUBMIT_FAIL_NULL_LOG": "No diagnosis result",
  "DIAGNOSE_DOING_TITLE": "Being diagnosed...",
  "DIAGNOSE_DOING_DESC": "Don't leave this page to avoid affecting the diagnosis process",
  "LOG_OUT_DELETE_OTHER_DEVICE": "Before you close an APP account, please delete devices first so as to ensure these devices can be added to other APP accounts successfully later on.",
  "SURE_DELETE_NOW": "Delete immediately",
  "DELETE_SUCCESS": "Delete successfully",
  "DELETE_FAILED": "Fail to delete, please try again",
  "NET_EXCEPTION_RETRY": "Network error, please try again later",
  "MEARI_BACK_MAIN_SCREEN": "Homepage",
  "MEARI_GO_LIST": "Device List",
  "CONNECT_SERVER_FAILED": "Server Connection Failure",
  "FEEDBACK_USER_CALL_TITLE": "Please fill in your name(Optional)",
  "KAI_WEI_SEARCH_FAIL": "Search failure! Please check the eWeLink router connections.",
  "FEEDBACK_INPUT_THEME": "Please enter a theme.",
  "rolling_door_child_lock_on": "The child lock open",
  "rolling_door_child_lock_off": "The child lock close",
  "rolling_door_pull_up": "Open",
  "rolling_door_pull_down": "Close",
  "rolling_door_stop": "Stop",
  "rolling_door_camera": "Camera",
  "rolling_door_status": "Status",
  "rolling_door_status_0": "Normal",
  "rolling_door_status_1": "Stop if an obstacle is detected",
  "rolling_door_status_2": "Bounce for 3s after obstacle",
  "rolling_door_status_3": "Process checking",
  "rolling_door_status_4": "Bounce to top after obstacle",
  "rolling_door_status_5": "Opened",
  "rolling_door_status_6": "Closed",
  "rolling_door_set_0": "Disable Obstacle Detection",
  "rolling_door_set_1": "Stop if an obstacle is detected",
  "rolling_door_set_2": "Bounce for 3s after obstacle",
  "rolling_door_set_3": "Bounce to top after obstacle",
  "rolling_door_open_percentage": "Open in proportion",
  "rolling_door_add_camera": "Add cameras",
  "rolling_door_motor_function_set": "Motor settings",
  "rolling_door_current_position": "Current position",
  "KAI_WEI_SEARCH_BIND": "Bind instantly",
  "KAI_WEI_SEARCH_FAIL_OTHER": "It¡¯s been bound to another account",
  "KAI_WEI_SEARCH_BIND_FAIL": "Bind failure. Please try again",
  "KAI_WEI_SEARCH_SUCCESS": "Search success",
  "KAI_WEI_SEARCH_INPUT_PWD": "Please enter your eWeLink password for account binding",
  "KAI_WEI_SEARCH_INPUT_PWD_TEXT": "Enter the password",
  "KAI_WEI_SEARCH_FAIL_OWN": "Your account has been bound",
  "KAI_WEI_SEARCH_BIND_SUCCESS": "Account binding success",
  "KAI_WEI_ROUTER_ONE_KEY_CONNECT": "One-Click Pairing",
  "KAI_WEI_ROUTER_ONE_KEY_PAIRING_SUCCESS": "Success. The router is ready to enter pairing mode",
  "KAI_WEI_ROUTER_UNBIND": "Unbind",
  "KAI_WEI_ROUTER_UNBIND_ERROR_501": "Invalid parameter",
  "KAI_WEI_ROUTER_UNBIND_ERROR_503": "Error: wrong username",
  "KAI_WEI_ROUTER_UNBIND_ERROR_504": "Error, unbind failure",
  "KAI_WEI_ROUTER_UNBIND_ERROR_505": "Error: wrong password",
  "KAI_WEI_SEARCH_INPUT_PWD_UNBIND": "Please enter your eWeLink password for account unbinding",
  "KAI_WEI_SEARCH_INPUT_PWD_PASSWORD_CHANGE": "Password error. Please sync the right password to the router.",
  "KAI_WEI_PASSWORD_CHANGE_SYNCHRONOUS": "Synchronize the router",
  "KAI_WEI_CHANGE_PWD_UNBIND_DELETE": "Your router has been unbound successfully via other means (eg. Router Management Interface)",
  "DOWNLOAD": "Record the downloads",
  "POWER_REFRESH_SUCCESS": "Refreshed successfully",
  "NEW_HUMIDIFIER_LACK_OF_WATER_CANNOT_OPERATE": "Do Not Operate due to lack of water",
  "YOUQIAO_MAX_VALUE_POWER_RANGE": "The value is out of range. The range of the maximum power value is 10-3300W",
  "YOUQIAO_MIN_VALUE_POWER_RANGE": "The value is out of range. The range of the minimum power value is 0.1-3300W",
  "YOUQIAO_ELECTRIC_RANGE": "The value is out of range. The current range is 0.1-15A",
  "YOUQIAO_VALTAGE_RANGE": "The value is out of range. The voltage range is 0.1-300V",
  "RATE_RANGE": "The value is out of range. The rate of fees range is 0-1000",
  "COLD_WARM_LED_COLD_LIGHT": "Cold light",
  "COLD_WARM_LED_WARM_LIGHT": "Warm light",
  "COLD_WARM_LED_MIDDLE_LIGHT": "Neutral light",
  "FEEDBACK_Appellation_LIMIT": "Please ensure that your name is not more than 15 characters",
  "ROLLING_DOOR_CAMERA_OFFLINE": "The camera status is offline",
  "MEARI_PERSON_CHECK": "Human detection",
  "MEARI_NICKNAME_LENGTH": "Please enter a valid username",
  "MEARI_WIFI_PIR_DES": "One-Click Pairing",
  "CAMERA_DEVICE_OFFLINE": "The camera status is offline",
  "INCHING_RANGE": "Inching  duration should be  integral multiple of  500 ，between 500~36,000,000 seconds.",
  "INCHING_TIME_SWITCH": "  enable inching  duration ",
  "INCHING_ENABLE": "will work only if inching duration is enabled",
  "INCHING_TIME_SETTING": " enable inching  duration ",
  "PLUSE_SWITCH": " disable Indicator",
  "PLUSE_SWITCH_NOTICE": " disable indicator light of device "
}